Workbook

Sheet Read Me
B2: INVOICE CHASER — SaaS Financial Model
B3: Automated invoice follow-up for French auto-entrepreneurs · 36-month monthly build
B5: HOW TO USE THIS MODEL
B6: Change one cell to re-run | C6: Assumptions!B5 is the scenario switch. Enter 1 (Conservative), 2 (Base) or 3 (Aggressive). Every sheet recalculates from it. Example: set B5 = 3 and the Dashboard repoints to the Aggressive case.
B7: Change the drivers | C7: On Assumptions, edit columns C, D and E (the three scenario columns). Column F is the LIVE column — it is a formula, do not type over it. Everything downstream reads column F only.
B8: Nothing else is an input | C8: Cohorts, P&L, Cash Flow, Unit Economics and Dashboard are 100% formula-driven. If you need to change a number, change it on Assumptions.
B10: COLOUR LEGEND
B11: Blue text | C11: Hardcoded input. Safe to edit.
B12: Yellow fill | C12: Key lever — the cells worth stress-testing first.
B13: Black text | C13: Formula. Do not overwrite.
B14: Green text | C14: Link to another sheet. Do not overwrite.
B16: SHEET MAP
B17: Assumptions | C17: All drivers, three scenarios side by side, plus a derived block (ARPU, blended churn, implied lifetime).
B18: Cohorts | C18: Acquisition funnel, then two 36x36 cohort waterfalls — one for monthly plans (constant monthly churn), one for annual plans (no churn inside the committed year, renewal decision at each 12-month anniversary).
B19: P&L | C19: Billings vs recognised revenue, cost of revenue, gross margin, opex, EBITDA.
B20: Cash Flow | C20: Cash walk plus a deferred revenue rollforward for annual prepayments, and an integrity check row.
B21: Unit Economics | C21: LTV, CAC (paid and blended), payback, LTV:CAC, and two sensitivity grids.
B22: Dashboard | C22: Headline outputs, breakeven months, funding requirement, NPV, and two charts.
B24: HOW THE ANNUAL PLAN IS MODELLED
B25: Why it matters | C25: Annual prepayment is the single biggest cash lever a low-ticket SaaS has. Ignoring it overstates the funding gap; treating cash as revenue overstates the P&L. This model separates the two.
B26: Billings | C26: An annual customer is charged 10x the monthly price upfront (2 months free) in their cohort month, and again at each anniversary if they renew.
B27: Revenue | C27: Recognised straight-line: 10/12 of the monthly price, each month, for 12 months.
B28: The difference | C28: Sits in deferred revenue on the Cash Flow sheet. Cash Flow row 22 checks that Net cash flow − EBITDA − Δdeferred = 0 in every month. It must read zero across the row.
B30: HEALTH WARNING ON THE NUMBERS
B31: These are benchmarks, not evidence | C31: Every operating assumption here is a placeholder drawn from typical low-ticket, self-serve B2B SaaS ranges. None of it is observed data for this product. The model is a decision framework, not a forecast.
B32: The three that decide the business | C32: Monthly churn, trial-to-paid conversion, and blended CPC. The Unit Economics sensitivity grids show that the verdict flips inside plausible ranges of these three — so they are what validation has to resolve first.
B33: Cheapest way to test them | C33: Churn and conversion need a landing page and ~20 customer conversations, not a spreadsheet. CPC can be read off a €200 test campaign in a week. Do that before trusting any output on the Dashboard.
B34: Not modelled | C34: VAT/TVA treatment, corporate tax, any founder opportunity cost beyond the salary line, and competitive response. Add them before this goes in front of anyone external.

Sheet Assumptions
A2: ASSUMPTIONS & SCENARIO DRIVERS
A3: Edit columns C–E only. Column F is the live selection and feeds every other sheet.
A5: Scenario switch (1 = Conservative, 2 = Base, 3 = Aggressive) | B5: 2
A6: Active scenario | B6: =INDEX(C6:E6,$B$5) -> Base | C6: Conservative | D6: Base | E6: Aggressive
A8: Driver | B8: Unit | C8: Conservative | D8: Base | E8: Aggressive | F8: LIVE | G8: Basis / how to validate
A9: PRICING & PLANS
A10: Solo plan price | B10: € / month | C10: 9 | D10: 9 | E10: 12 | F10: =INDEX(C10:E10,$B$5) -> 9 | G10: Placeholder. Anchored below what a comptable charges for the same chasing. Validate with pricing interviews.
A11: Pro plan price | B11: € / month | C11: 19 | D11: 19 | E11: 24 | F11: =INDEX(C11:E11,$B$5) -> 19 | G11: Placeholder. Pro = multi-client, custom sequences, reminders by SMS.
A12: Pro plan share of customers | B12: % of customers | C12: 0.2 | D12: 0.3 | E12: 0.35 | F12: =INDEX(C12:E12,$B$5) -> 0.3 | G12: Placeholder. Share of base on the higher tier.
A13: Annual plan share of new customers | B13: % of new | C13: 0.15 | D13: 0.2 | E13: 0.25 | F13: =INDEX(C13:E13,$B$5) -> 0.2 | G13: Key cash lever. Self-serve SaaS at this price point rarely pushes past ~25% annual without a hard discount.
A14: Annual plan — months free vs 12x monthly | B14: months | C14: 2 | D14: 2 | E14: 2 | F14: =INDEX(C14:E14,$B$5) -> 2 | G14: Standard 2-months-free annual offer, i.e. pay for 10, get 12.
A15: ACQUISITION
A16: Paid marketing spend, month 1 | B16: € / month | C16: 300 | D16: 500 | E16: 900 | F16: =INDEX(C16:E16,$B$5) -> 500 | G16: Founder-funded test budget in month 1.
A17: Paid spend growth | B17: % / month | C17: 0.06 | D17: 0.08 | E17: 0.1 | F17: =INDEX(C17:E17,$B$5) -> 0.08 | G17: Reinvestment pace. Deliberately slow — spend is capped below.
A18: Paid spend ceiling | B18: € / month | C18: 3000 | D18: 6000 | E18: 12000 | F18: =INDEX(C18:E18,$B$5) -> 6000 | G18: Ceiling. Reflects a genuinely narrow niche — French micro-entrepreneurs searching for invoice chasing. The addressable paid inventory runs out.
A19: Blended cost per click | B19: € | C19: 1.1 | D19: 0.8 | E19: 0.6 | F19: =INDEX(C19:E19,$B$5) -> 0.8 | G19: Key lever. Placeholder for French-language Google/Meta on low-competition long-tail terms. Testable for ~€200 in one week — do this first.
A20: Landing page → free trial | B20: % | C20: 0.025 | D20: 0.04 | E20: 0.055 | F20: =INDEX(C20:E20,$B$5) -> 0.04 | G20: Placeholder. Typical range for a self-serve tool with a clear single job-to-be-done.
A21: Free trial → paid | B21: % | C21: 0.15 | D21: 0.22 | E21: 0.28 | F21: =INDEX(C21:E21,$B$5) -> 0.22 | G21: Key lever. Trial-to-paid for no-credit-card self-serve trials. Drives CAC almost as hard as CPC.
A22: Organic trials, month 1 | B22: trials | C22: 10 | D22: 20 | E22: 35 | F22: =INDEX(C22:E22,$B$5) -> 20 | G22: Content/SEO and community (forums, LinkedIn, auto-entrepreneur groups). Zero marginal cost, slow to build.
A23: Organic trial growth | B23: % / month | C23: 0.08 | D23: 0.12 | E23: 0.16 | F23: =INDEX(C23:E23,$B$5) -> 0.12 | G23: Compounding content effect.
A24: Organic trial ceiling | B24: trials / month | C24: 150 | D24: 400 | E24: 800 | F24: =INDEX(C24:E24,$B$5) -> 400 | G24: Ceiling. Organic demand for this niche is finite.
A25: Referral trials per active customer | B25: / month | C25: 0.005 | D25: 0.015 | E25: 0.03 | F25: =INDEX(C25:E25,$B$5) -> 0.015 | G25: Word of mouth. Freelancers talk, but they are not a dense network.
A26: RETENTION
A27: Monthly-plan gross churn | B27: % / month | C27: 0.08 | D27: 0.06 | E27: 0.045 | F27: =INDEX(C27:E27,$B$5) -> 0.06 | G27: Single most important assumption. High by SaaS standards because the customer base itself churns — micro-entrepreneurs deregister, go salaried, or stop invoicing. This is not a product-quality number.
A28: Annual-plan renewal rate at each anniversary | B28: % | C28: 0.6 | D28: 0.7 | E28: 0.8 | F28: =INDEX(C28:E28,$B$5) -> 0.7 | G28: Applied once every 12 months. Annual customers cannot churn mid-commitment.
A29: COST OF REVENUE
A30: Infrastructure & automation per customer | B30: € / cust / month | C30: 0.45 | D30: 0.35 | E30: 0.28 | F30: =INDEX(C30:E30,$B$5) -> 0.35 | G30: n8n execution volume, storage, API calls. Falls with scale as fixed capacity is absorbed.
A31: Email & messaging per customer | B31: € / cust / month | C31: 0.15 | D31: 0.1 | E31: 0.08 | F31: =INDEX(C31:E31,$B$5) -> 0.1 | G31: Transactional email volume — each customer sends multiple reminder sequences per month.
A32: Support cost per customer | B32: € / cust / month | C32: 0.5 | D32: 0.3 | E32: 0.2 | F32: =INDEX(C32:E32,$B$5) -> 0.3 | G32: Founder time costed at a notional rate. At €9/month, support is what kills the margin — watch this line.
A33: Payment processing — % of billings | B33: % | C33: 0.015 | D33: 0.015 | E33: 0.015 | F33: =INDEX(C33:E33,$B$5) -> 0.015 | G33: Stripe standard European card rate. Verify against current Stripe pricing before relying on it.
A34: Payment processing — fee per transaction | B34: € | C34: 0.25 | D34: 0.25 | E34: 0.25 | F34: =INDEX(C34:E34,$B$5) -> 0.25 | G34: Stripe per-transaction fee. This is why annual billing helps margin, not just cash — one charge, not twelve.
A35: Fixed platform cost | B35: € / month | C35: 90 | D35: 70 | E35: 70 | F35: =INDEX(C35:E35,$B$5) -> 70 | G35: n8n cloud plan, hosting baseline, domain. Does not scale with customers.
A36: OPERATING EXPENSES
A37: Founder compensation once drawn | B37: € / month | C37: 1500 | D37: 2500 | E37: 3500 | F37: =INDEX(C37:E37,$B$5) -> 2500 | G37: Set by you. Note this is a side project — the real cost is hours, not euros, until this line switches on.
A38: First month founder is paid | B38: month # | C38: 13 | D38: 13 | E38: 10 | F38: =INDEX(C38:E38,$B$5) -> 13 | G38: Key lever. The month the business stops being free to run. Moving this earlier is the fastest way to break the cash line.
A39: Tools & software | B39: € / month | C39: 150 | D39: 120 | E39: 120 | F39: =INDEX(C39:E39,$B$5) -> 120 | G39: Stripe dashboard extras, analytics, design, hosting for the marketing site.
A40: Legal, accounting & admin | B40: € / month | C40: 120 | D40: 80 | E40: 80 | F40: =INDEX(C40:E40,$B$5) -> 80 | G40: Accountant, company admin, CGU/RGPD review. RGPD matters here — the product touches client contact data.
A41: Fixed opex inflation | B41: % / month | C41: 0.005 | D41: 0.005 | E41: 0.005 | F41: =INDEX(C41:E41,$B$5) -> 0.005 | G41: Applied to tools and admin only. ~6% annualised.
A42: FINANCING & VALUATION
A43: Opening cash (founder contribution) | B43: € | C43: 5000 | D43: 5000 | E43: 5000 | F43: =INDEX(C43:E43,$B$5) -> 5000 | G43: Set by you. The model tells you whether this is enough.
A44: Discount rate | B44: % / year | C44: 0.3 | D44: 0.25 | E44: 0.2 | F44: =INDEX(C44:E44,$B$5) -> 0.25 | G44: Pre-revenue, single-founder, unvalidated demand. High rate is doing real work here, not decoration.
A45: DERIVED (calculated — do not edit)
A46: Blended list price — monthly plan | B46: € / month | F46: =Assumptions!$F$10*(1-Assumptions!$F$12)+Assumptions!$F$11*Assumptions!$F$12 -> 12 | G46: Weighted by Pro mix.
A47: Effective ARPU — annual plan | B47: € / month | F47: =Assumptions!$F$46*(12-Assumptions!$F$14)/12 -> 10 | G47: Recognised straight-line over 12 months after the 2-months-free discount.
A48: Blended ARPU — all plans | B48: € / month | F48: =Assumptions!$F$46*(1-Assumptions!$F$13)+Assumptions!$F$47*Assumptions!$F$13 -> 11.6 | G48: Used for LTV.
A49: Annual plan — cash charged upfront | B49: € | F49: =Assumptions!$F$46*(12-Assumptions!$F$14) -> 120 | G49: Billed in the cohort month and at each renewal.
A50: Annual plan — monthly-equivalent churn | B50: % / month | F50: =1-Assumptions!$F$28^(1/12) -> 0.02928553 | G50: Anniversary renewal rate expressed as an equivalent constant monthly rate, for the blend below.
A51: Blended monthly churn | B51: % / month | F51: =Assumptions!$F$27*(1-Assumptions!$F$13)+Assumptions!$F$50*Assumptions!$F$13 -> 0.053857106 | G51: Weighted by plan mix. This is the churn that drives LTV.
A52: Implied average customer lifetime | B52: months | F52: =IF(Assumptions!$F$51=0,0,1/Assumptions!$F$51) -> 18.567652 | G52: 1 / blended churn.
A53: Paid CAC (from funnel maths) | B53: € | F53: =IF(Assumptions!$F$20*Assumptions!$F$21=0,0,Assumptions!$F$19/(Assumptions!$F$20*Assumptions!$F$21)) -> 90.909091 | G53: CPC / (signup rate x trial-to-paid). Cost to buy one paying customer through paid channels.
A54: Monthly discount rate | B54: % / month | F54: =(1+Assumptions!$F$44)^(1/12)-1 -> 0.018769265 | G54: Annual rate de-annualised for the monthly NPV.

Sheet Cohorts
A2: COHORT ENGINE
A3: Acquisition funnel, then customer waterfalls by cohort. Monthly plans churn every month; annual plans are locked for 12 and face a renewal decision at each anniversary.
A5: Month index | B5: # | C5: 1 | D5: 2 | E5: 3 | F5: 4 | G5: 5 | H5: 6 | I5: 7 | J5: 8 | K5: 9 | L5: 10 | M5: 11 | N5: 12 | O5: 13 | P5: 14 | Q5: 15 | R5: 16 | S5: 17 | T5: 18 | U5: 19 | V5: 20 | W5: 21 | X5: 22 | Y5: 23 | Z5: 24 | AA5: 25 | AB5: 26 | AC5: 27 | AD5: 28 | AE5: 29 | AF5: 30 | AG5: 31 | AH5: 32 | AI5: 33 | AJ5: 34 | AK5: 35 | AL5: 36
A7: ACQUISITION FUNNEL
A8: Paid marketing spend | B8: € | C8: =MIN(Assumptions!$F$18,Assumptions!$F$16*(1+Assumptions!$F$17)^(C5-1)) -> 500 | D8: =MIN(Assumptions!$F$18,Assumptions!$F$16*(1+Assumptions!$F$17)^(D5-1)) -> 540 | E8: =MIN(Assumptions!$F$18,Assumptions!$F$16*(1+Assumptions!$F$17)^(E5-1)) -> 583.2 | F8: =MIN(Assumptions!$F$18,Assumptions!$F$16*(1+Assumptions!$F$17)^(F5-1)) -> 629.856 | G8: =MIN(Assumptions!$F$18,Assumptions!$F$16*(1+Assumptions!$F$17)^(G5-1)) -> 680.24448 | H8: =MIN(Assumptions!$F$18,Assumptions!$F$16*(1+Assumptions!$F$17)^(H5-1)) -> 734.66404 | I8: =MIN(Assumptions!$F$18,Assumptions!$F$16*(1+Assumptions!$F$17)^(I5-1)) -> 793.43716 | J8: =MIN(Assumptions!$F$18,Assumptions!$F$16*(1+Assumptions!$F$17)^(J5-1)) -> 856.91213 | ... AL8: =MIN(Assumptions!$F$18,Assumptions!$F$16*(1+Assumptions!$F$17)^(AL5-1)) -> 6000
A9: Paid visitors | B9: # | C9: =IF(Assumptions!$F$19=0,0,C8/Assumptions!$F$19) -> 625 | D9: =IF(Assumptions!$F$19=0,0,D8/Assumptions!$F$19) -> 675 | E9: =IF(Assumptions!$F$19=0,0,E8/Assumptions!$F$19) -> 729 | F9: =IF(Assumptions!$F$19=0,0,F8/Assumptions!$F$19) -> 787.32 | G9: =IF(Assumptions!$F$19=0,0,G8/Assumptions!$F$19) -> 850.3056 | H9: =IF(Assumptions!$F$19=0,0,H8/Assumptions!$F$19) -> 918.33005 | I9: =IF(Assumptions!$F$19=0,0,I8/Assumptions!$F$19) -> 991.79645 | J9: =IF(Assumptions!$F$19=0,0,J8/Assumptions!$F$19) -> 1071.1402 | ... AL9: =IF(Assumptions!$F$19=0,0,AL8/Assumptions!$F$19) -> 7500
A10: Paid trials | B10: # | C10: =C9*Assumptions!$F$20 -> 25 | D10: =D9*Assumptions!$F$20 -> 27 | E10: =E9*Assumptions!$F$20 -> 29.16 | F10: =F9*Assumptions!$F$20 -> 31.4928 | G10: =G9*Assumptions!$F$20 -> 34.012224 | H10: =H9*Assumptions!$F$20 -> 36.733202 | I10: =I9*Assumptions!$F$20 -> 39.671858 | J10: =J9*Assumptions!$F$20 -> 42.845607 | ... AL10: =AL9*Assumptions!$F$20 -> 300
A11: Organic trials | B11: # | C11: =MIN(Assumptions!$F$24,Assumptions!$F$22*(1+Assumptions!$F$23)^(C5-1)) -> 20 | D11: =MIN(Assumptions!$F$24,Assumptions!$F$22*(1+Assumptions!$F$23)^(D5-1)) -> 22.4 | E11: =MIN(Assumptions!$F$24,Assumptions!$F$22*(1+Assumptions!$F$23)^(E5-1)) -> 25.088 | F11: =MIN(Assumptions!$F$24,Assumptions!$F$22*(1+Assumptions!$F$23)^(F5-1)) -> 28.09856 | G11: =MIN(Assumptions!$F$24,Assumptions!$F$22*(1+Assumptions!$F$23)^(G5-1)) -> 31.470387 | H11: =MIN(Assumptions!$F$24,Assumptions!$F$22*(1+Assumptions!$F$23)^(H5-1)) -> 35.246834 | I11: =MIN(Assumptions!$F$24,Assumptions!$F$22*(1+Assumptions!$F$23)^(I5-1)) -> 39.476454 | J11: =MIN(Assumptions!$F$24,Assumptions!$F$22*(1+Assumptions!$F$23)^(J5-1)) -> 44.213628 | ... AL11: =MIN(Assumptions!$F$24,Assumptions!$F$22*(1+Assumptions!$F$23)^(AL5-1)) -> 400
A12: Referral trials | B12: # | C12: =C22*Assumptions!$F$25 -> 0 | D12: =D22*Assumptions!$F$25 -> 0.1485 | E12: =E22*Assumptions!$F$25 -> 0.30488205 | F12: =F22*Assumptions!$F$25 -> 0.47035776 | G12: =G22*Assumptions!$F$25 -> 0.64624438 | H12: =H22*Assumptions!$F$25 -> 0.8339778 | I12: =I22*Assumptions!$F$25 -> 1.0351269 | J12: =J22*Assumptions!$F$25 -> 1.2514097 | ... AL12: =AL22*Assumptions!$F$25 -> 24.334608
A13: Total trials | B13: # | C13: =SUM(C10:C12) -> 45 | D13: =SUM(D10:D12) -> 49.5485 | E13: =SUM(E10:E12) -> 54.552882 | F13: =SUM(F10:F12) -> 60.061718 | G13: =SUM(G10:G12) -> 66.128856 | H13: =SUM(H10:H12) -> 72.814013 | I13: =SUM(I10:I12) -> 80.183439 | J13: =SUM(J10:J12) -> 88.310645 | ... AL13: =SUM(AL10:AL12) -> 724.33461
A14: New paying customers | B14: # | C14: =C13*Assumptions!$F$21 -> 9.9 | D14: =D13*Assumptions!$F$21 -> 10.90067 | E14: =E13*Assumptions!$F$21 -> 12.001634 | F14: =F13*Assumptions!$F$21 -> 13.213578 | G14: =G13*Assumptions!$F$21 -> 14.548348 | H14: =H13*Assumptions!$F$21 -> 16.019083 | I14: =I13*Assumptions!$F$21 -> 17.640357 | J14: =J13*Assumptions!$F$21 -> 19.428342 | ... AL14: =AL13*Assumptions!$F$21 -> 159.35361
A15: — new on monthly plan | B15: # | C15: =C14*(1-Assumptions!$F$13) -> 7.92 | D15: =D14*(1-Assumptions!$F$13) -> 8.720536 | E15: =E14*(1-Assumptions!$F$13) -> 9.6013072 | F15: =F14*(1-Assumptions!$F$13) -> 10.570862 | G15: =G14*(1-Assumptions!$F$13) -> 11.638679 | H15: =H14*(1-Assumptions!$F$13) -> 12.815266 | I15: =I14*(1-Assumptions!$F$13) -> 14.112285 | J15: =J14*(1-Assumptions!$F$13) -> 15.542673 | ... AL15: =AL14*(1-Assumptions!$F$13) -> 127.48289
A16: — new on annual plan | B16: # | C16: =C14*Assumptions!$F$13 -> 1.98 | D16: =D14*Assumptions!$F$13 -> 2.180134 | E16: =E14*Assumptions!$F$13 -> 2.4003268 | F16: =F14*Assumptions!$F$13 -> 2.6427156 | G16: =G14*Assumptions!$F$13 -> 2.9096696 | H16: =H14*Assumptions!$F$13 -> 3.2038166 | I16: =I14*Assumptions!$F$13 -> 3.5280713 | J16: =J14*Assumptions!$F$13 -> 3.8856684 | ... AL16: =AL14*Assumptions!$F$13 -> 31.870723
A18: ACTIVE CUSTOMERS
A19: Monthly-plan customers (closing) | B19: # | C19: =SUM(C27:C62) -> 7.92 | D19: =SUM(D27:D62) -> 16.165336 | E19: =SUM(E27:E62) -> 24.796723 | F19: =SUM(F27:F62) -> 33.879782 | G19: =SUM(G27:G62) -> 43.485674 | H19: =SUM(H27:H62) -> 53.6918 | I19: =SUM(I27:I62) -> 64.582577 | J19: =SUM(J27:J62) -> 76.250296 | ... AL19: =SUM(AL27:AL62) -> 1246.6676
A20: Annual-plan customers (closing) | B20: # | C20: =SUM(C66:C101) -> 1.98 | D20: =SUM(D66:D101) -> 4.160134 | E20: =SUM(E66:E101) -> 6.5604608 | F20: =SUM(F66:F101) -> 9.2031764 | G20: =SUM(G66:G101) -> 12.112846 | H20: =SUM(H66:H101) -> 15.316663 | I20: =SUM(I66:I101) -> 18.844734 | J20: =SUM(J66:J101) -> 22.730402 | ... AL20: =SUM(AL66:AL101) -> 456.71958
A21: Total active customers (closing) | B21: # | C21: =C19+C20 -> 9.9 | D21: =D19+D20 -> 20.32547 | E21: =E19+E20 -> 31.357184 | F21: =F19+F20 -> 43.082958 | G21: =G19+G20 -> 55.59852 | H21: =H19+H20 -> 69.008462 | I21: =I19+I20 -> 83.427311 | J21: =J19+J20 -> 98.980698 | ... AL21: =AL19+AL20 -> 1703.3872
A22: Total active customers (opening) | B22: # | C22: =0 -> 0 | D22: =C21 -> 9.9 | E22: =D21 -> 20.32547 | F22: =E21 -> 31.357184 | G22: =F21 -> 43.082958 | H22: =G21 -> 55.59852 | I22: =H21 -> 69.008462 | J22: =I21 -> 83.427311 | K22: =J21 -> 98.980698 | ... AL22: =AK21 -> 1622.3072
A23: Annual plans billed this month | B23: # | C23: =C16 -> 1.98 | D23: =D16 -> 2.180134 | E23: =E16 -> 2.4003268 | F23: =F16 -> 2.6427156 | G23: =G16 -> 2.9096696 | H23: =H16 -> 3.2038166 | I23: =I16 -> 3.5280713 | J23: =J16 -> 3.8856684 | ... N23: =N16 -> 5.7275006 | O23: =O16+O66 -> 7.7002881 | P23: =P16+P67 -> 8.4885795 | Q23: =Q16+Q68 -> 9.3594247 | R23: =R16+R69 -> 10.321823 | S23: =S16+S70 -> 11.385777 | T23: =T16+T71 -> 12.56241 | U23: =U16+U72 -> 13.864089 | V23: =V16+V73 -> 15.304572 | W23: =W16+W74 -> 16.899167 | X23: =X16+X75 -> 18.664904 | Y23: =Y16+Y76 -> 20.620743 | Z23: =Z16+Z77 -> 22.787788 | AA23: =AA16+AA78+AA66 -> 26.159735 | AB23: =AB16+AB79+AB67 -> 28.919869 | AC23: =AC16+AC80+AC68 -> 31.979793 | AD23: =AD16+AD81+AD69 -> 34.207122 | AE23: =AE16+AE82+AE70 -> 35.715224 | AF23: =AF16+AF83+AF71 -> 37.358068 | AG23: =AG16+AG84+AG72 -> 39.149012 | AH23: =AH16+AH85+AH73 -> 41.102749 | AI23: =AI16+AI86+AI74 -> 43.235448 | AJ23: =AJ16+AJ87+AJ75 -> 44.821254 | AK23: =AK16+AK88+AK76 -> 46.249135 | AL23: =AL16+AL89+AL77 -> 47.822174
A24: New annual sign-ups plus the cohorts hitting their 12- and 24-month anniversary (post-renewal count).
A25: COHORT WATERFALL — MONTHLY PLAN (active customers)
A26: Cohort ↓ / Month → | B26: # | C26: 1 | D26: 2 | E26: 3 | F26: 4 | G26: 5 | H26: 6 | I26: 7 | J26: 8 | K26: 9 | L26: 10 | M26: 11 | N26: 12 | O26: 13 | P26: 14 | Q26: 15 | R26: 16 | S26: 17 | T26: 18 | U26: 19 | V26: 20 | W26: 21 | X26: 22 | Y26: 23 | Z26: 24 | AA26: 25 | AB26: 26 | AC26: 27 | AD26: 28 | AE26: 29 | AF26: 30 | AG26: 31 | AH26: 32 | AI26: 33 | AJ26: 34 | AK26: 35 | AL26: 36
A27: Cohort M1 | B27: # | C27: =C15 -> 7.92 | D27: =C27*(1-Assumptions!$F$27) -> 7.4448 | E27: =D27*(1-Assumptions!$F$27) -> 6.998112 | F27: =E27*(1-Assumptions!$F$27) -> 6.5782253 | G27: =F27*(1-Assumptions!$F$27) -> 6.1835318 | H27: =G27*(1-Assumptions!$F$27) -> 5.8125199 | I27: =H27*(1-Assumptions!$F$27) -> 5.4637687 | J27: =I27*(1-Assumptions!$F$27) -> 5.1359425 | K27: =J27*(1-Assumptions!$F$27) -> 4.827786 | ... AL27: =AK27*(1-Assumptions!$F$27) -> 0.90823881
A28: Cohort M2 | B28: # | C28: 0 | D28: =D15 -> 8.720536 | E28: =D28*(1-Assumptions!$F$27) -> 8.1973038 | F28: =E28*(1-Assumptions!$F$27) -> 7.7054656 | G28: =F28*(1-Assumptions!$F$27) -> 7.2431377 | H28: =G28*(1-Assumptions!$F$27) -> 6.8085494 | I28: =H28*(1-Assumptions!$F$27) -> 6.4000364 | J28: =I28*(1-Assumptions!$F$27) -> 6.0160343 | K28: =J28*(1-Assumptions!$F$27) -> 5.6550722 | L28: =K28*(1-Assumptions!$F$27) -> 5.3157679 | ... AL28: =AK28*(1-Assumptions!$F$27) -> 1.063874
A29: Cohort M3 | B29: # | C29: 0 | D29: 0 | E29: =E15 -> 9.6013072 | F29: =E29*(1-Assumptions!$F$27) -> 9.0252288 | G29: =F29*(1-Assumptions!$F$27) -> 8.4837151 | H29: =G29*(1-Assumptions!$F$27) -> 7.9746922 | I29: =H29*(1-Assumptions!$F$27) -> 7.4962106 | J29: =I29*(1-Assumptions!$F$27) -> 7.046438 | K29: =J29*(1-Assumptions!$F$27) -> 6.6236517 | L29: =K29*(1-Assumptions!$F$27) -> 6.2262326 | M29: =L29*(1-Assumptions!$F$27) -> 5.8526587 | ... AL29: =AK29*(1-Assumptions!$F$27) -> 1.2460904
A30: Cohort M4 | B30: # | C30: 0 | D30: 0 | E30: 0 | F30: =F15 -> 10.570862 | G30: =F30*(1-Assumptions!$F$27) -> 9.9366106 | H30: =G30*(1-Assumptions!$F$27) -> 9.340414 | I30: =H30*(1-Assumptions!$F$27) -> 8.7799891 | J30: =I30*(1-Assumptions!$F$27) -> 8.2531898 | K30: =J30*(1-Assumptions!$F$27) -> 7.7579984 | L30: =K30*(1-Assumptions!$F$27) -> 7.2925185 | M30: =L30*(1-Assumptions!$F$27) -> 6.8549674 | N30: =M30*(1-Assumptions!$F$27) -> 6.4436693 | ... AL30: =AK30*(1-Assumptions!$F$27) -> 1.459492
A31: Cohort M5 | B31: # | C31: 0 | D31: 0 | E31: 0 | F31: 0 | G31: =G15 -> 11.638679 | H31: =G31*(1-Assumptions!$F$27) -> 10.940358 | I31: =H31*(1-Assumptions!$F$27) -> 10.283936 | J31: =I31*(1-Assumptions!$F$27) -> 9.6669002 | K31: =J31*(1-Assumptions!$F$27) -> 9.0868862 | L31: =K31*(1-Assumptions!$F$27) -> 8.541673 | M31: =L31*(1-Assumptions!$F$27) -> 8.0291726 | N31: =M31*(1-Assumptions!$F$27) -> 7.5474223 | O31: =N31*(1-Assumptions!$F$27) -> 7.0945769 | ... AL31: =AK31*(1-Assumptions!$F$27) -> 1.7094923
A32: Cohort M6 | B32: # | C32: 0 | D32: 0 | E32: 0 | F32: 0 | G32: 0 | H32: =H15 -> 12.815266 | I32: =H32*(1-Assumptions!$F$27) -> 12.04635 | J32: =I32*(1-Assumptions!$F$27) -> 11.323569 | K32: =J32*(1-Assumptions!$F$27) -> 10.644155 | L32: =K32*(1-Assumptions!$F$27) -> 10.005506 | M32: =L32*(1-Assumptions!$F$27) -> 9.4051755 | N32: =M32*(1-Assumptions!$F$27) -> 8.840865 | O32: =N32*(1-Assumptions!$F$27) -> 8.3104131 | P32: =O32*(1-Assumptions!$F$27) -> 7.8117883 | ... AL32: =AK32*(1-Assumptions!$F$27) -> 2.0024572
A33: Cohort M7 | B33: # | C33: 0 | D33: 0 | E33: 0 | F33: 0 | G33: 0 | H33: 0 | I33: =I15 -> 14.112285 | J33: =I33*(1-Assumptions!$F$27) -> 13.265548 | K33: =J33*(1-Assumptions!$F$27) -> 12.469615 | L33: =K33*(1-Assumptions!$F$27) -> 11.721438 | M33: =L33*(1-Assumptions!$F$27) -> 11.018152 | N33: =M33*(1-Assumptions!$F$27) -> 10.357063 | O33: =N33*(1-Assumptions!$F$27) -> 9.7356391 | P33: =O33*(1-Assumptions!$F$27) -> 9.1515008 | Q33: =P33*(1-Assumptions!$F$27) -> 8.6024107 | ... AL33: =AK33*(1-Assumptions!$F$27) -> 2.3458763
A34: Cohort M8 | B34: # | C34: 0 | D34: 0 | E34: 0 | F34: 0 | G34: 0 | H34: 0 | I34: 0 | J34: =J15 -> 15.542673 | K34: =J34*(1-Assumptions!$F$27) -> 14.610113 | L34: =K34*(1-Assumptions!$F$27) -> 13.733506 | M34: =L34*(1-Assumptions!$F$27) -> 12.909496 | N34: =M34*(1-Assumptions!$F$27) -> 12.134926 | O34: =N34*(1-Assumptions!$F$27) -> 11.406831 | P34: =O34*(1-Assumptions!$F$27) -> 10.722421 | Q34: =P34*(1-Assumptions!$F$27) -> 10.079075 | R34: =Q34*(1-Assumptions!$F$27) -> 9.4743309 | ... AL34: =AK34*(1-Assumptions!$F$27) -> 2.7485625
A35: Cohort M9 | B35: # | C35: 0 | D35: 0 | E35: 0 | F35: 0 | G35: 0 | H35: 0 | I35: 0 | J35: 0 | K35: =K15 -> 17.120792 | L35: =K35*(1-Assumptions!$F$27) -> 16.093545 | M35: =L35*(1-Assumptions!$F$27) -> 15.127932 | N35: =M35*(1-Assumptions!$F$27) -> 14.220256 | O35: =N35*(1-Assumptions!$F$27) -> 13.367041 | P35: =O35*(1-Assumptions!$F$27) -> 12.565018 | Q35: =P35*(1-Assumptions!$F$27) -> 11.811117 | R35: =Q35*(1-Assumptions!$F$27) -> 11.10245 | S35: =R35*(1-Assumptions!$F$27) -> 10.436303 | ... AL35: =AK35*(1-Assumptions!$F$27) -> 3.2208901
A36: Cohort M10 | B36: # | C36: 0 | D36: 0 | E36: 0 | F36: 0 | G36: 0 | H36: 0 | I36: 0 | J36: 0 | K36: 0 | L36: =L15 -> 18.862587 | M36: =L36*(1-Assumptions!$F$27) -> 17.730832 | N36: =M36*(1-Assumptions!$F$27) -> 16.666982 | O36: =N36*(1-Assumptions!$F$27) -> 15.666963 | P36: =O36*(1-Assumptions!$F$27) -> 14.726945 | Q36: =P36*(1-Assumptions!$F$27) -> 13.843329 | R36: =Q36*(1-Assumptions!$F$27) -> 13.012729 | S36: =R36*(1-Assumptions!$F$27) -> 12.231965 | T36: =S36*(1-Assumptions!$F$27) -> 11.498047 | ... AL36: =AK36*(1-Assumptions!$F$27) -> 3.7750739
A37: Cohort M11 | B37: # | C37: 0 | D37: 0 | E37: 0 | F37: 0 | G37: 0 | H37: 0 | I37: 0 | J37: 0 | K37: 0 | L37: 0 | M37: =M15 -> 20.785767 | N37: =M37*(1-Assumptions!$F$27) -> 19.538621 | O37: =N37*(1-Assumptions!$F$27) -> 18.366303 | P37: =O37*(1-Assumptions!$F$27) -> 17.264325 | Q37: =P37*(1-Assumptions!$F$27) -> 16.228466 | R37: =Q37*(1-Assumptions!$F$27) -> 15.254758 | S37: =R37*(1-Assumptions!$F$27) -> 14.339472 | T37: =S37*(1-Assumptions!$F$27) -> 13.479104 | U37: =T37*(1-Assumptions!$F$27) -> 12.670358 | ... AL37: =AK37*(1-Assumptions!$F$27) -> 4.4255004
A38: Cohort M12 | B38: # | C38: 0 | D38: 0 | E38: 0 | F38: 0 | G38: 0 | H38: 0 | I38: 0 | J38: 0 | K38: 0 | L38: 0 | M38: 0 | N38: =N15 -> 22.910002 | O38: =N38*(1-Assumptions!$F$27) -> 21.535402 | P38: =O38*(1-Assumptions!$F$27) -> 20.243278 | Q38: =P38*(1-Assumptions!$F$27) -> 19.028681 | R38: =Q38*(1-Assumptions!$F$27) -> 17.88696 | S38: =R38*(1-Assumptions!$F$27) -> 16.813743 | T38: =S38*(1-Assumptions!$F$27) -> 15.804918 | U38: =T38*(1-Assumptions!$F$27) -> 14.856623 | V38: =U38*(1-Assumptions!$F$27) -> 13.965226 | ... AL38: =AK38*(1-Assumptions!$F$27) -> 5.1891189
A39: Cohort M13 | B39: # | C39: 0 | D39: 0 | E39: 0 | F39: 0 | G39: 0 | H39: 0 | I39: 0 | J39: 0 | K39: 0 | L39: 0 | M39: 0 | N39: 0 | O39: =O15 -> 25.257153 | P39: =O39*(1-Assumptions!$F$27) -> 23.741723 | Q39: =P39*(1-Assumptions!$F$27) -> 22.31722 | R39: =Q39*(1-Assumptions!$F$27) -> 20.978187 | S39: =R39*(1-Assumptions!$F$27) -> 19.719496 | T39: =S39*(1-Assumptions!$F$27) -> 18.536326 | U39: =T39*(1-Assumptions!$F$27) -> 17.424146 | V39: =U39*(1-Assumptions!$F$27) -> 16.378698 | W39: =V39*(1-Assumptions!$F$27) -> 15.395976 | ... AL39: =AK39*(1-Assumptions!$F$27) -> 6.0859029
A40: Cohort M14 | B40: # | C40: 0 | D40: 0 | E40: 0 | F40: 0 | G40: 0 | H40: 0 | I40: 0 | J40: 0 | K40: 0 | L40: 0 | M40: 0 | N40: 0 | O40: 0 | P40: =P15 -> 27.849943 | Q40: =P40*(1-Assumptions!$F$27) -> 26.178946 | R40: =Q40*(1-Assumptions!$F$27) -> 24.608209 | S40: =R40*(1-Assumptions!$F$27) -> 23.131717 | T40: =S40*(1-Assumptions!$F$27) -> 21.743814 | U40: =T40*(1-Assumptions!$F$27) -> 20.439185 | V40: =U40*(1-Assumptions!$F$27) -> 19.212834 | W40: =V40*(1-Assumptions!$F$27) -> 18.060064 | X40: =W40*(1-Assumptions!$F$27) -> 16.97646 | ... AL40: =AK40*(1-Assumptions!$F$27) -> 7.1389952
A41: Cohort M15 | B41: # | C41: 0 | D41: 0 | E41: 0 | F41: 0 | G41: 0 | H41: 0 | I41: 0 | J41: 0 | K41: 0 | L41: 0 | M41: 0 | N41: 0 | O41: 0 | P41: 0 | Q41: =Q15 -> 30.716784 | R41: =Q41*(1-Assumptions!$F$27) -> 28.873777 | S41: =R41*(1-Assumptions!$F$27) -> 27.14135 | T41: =S41*(1-Assumptions!$F$27) -> 25.512869 | U41: =T41*(1-Assumptions!$F$27) -> 23.982097 | V41: =U41*(1-Assumptions!$F$27) -> 22.543171 | W41: =V41*(1-Assumptions!$F$27) -> 21.190581 | X41: =W41*(1-Assumptions!$F$27) -> 19.919146 | Y41: =X41*(1-Assumptions!$F$27) -> 18.723997 | ... AL41: =AK41*(1-Assumptions!$F$27) -> 8.3764628
A42: Cohort M16 | B42: # | C42: 0 | D42: 0 | E42: 0 | F42: 0 | G42: 0 | H42: 0 | I42: 0 | J42: 0 | K42: 0 | L42: 0 | M42: 0 | N42: 0 | O42: 0 | P42: 0 | Q42: 0 | R42: =R15 -> 33.887688 | S42: =R42*(1-Assumptions!$F$27) -> 31.854427 | T42: =S42*(1-Assumptions!$F$27) -> 29.943161 | U42: =T42*(1-Assumptions!$F$27) -> 28.146571 | V42: =U42*(1-Assumptions!$F$27) -> 26.457777 | W42: =V42*(1-Assumptions!$F$27) -> 24.87031 | X42: =W42*(1-Assumptions!$F$27) -> 23.378092 | Y42: =X42*(1-Assumptions!$F$27) -> 21.975406 | Z42: =Y42*(1-Assumptions!$F$27) -> 20.656882 | ... AL42: =AK42*(1-Assumptions!$F$27) -> 9.8310297
A43: Cohort M17 | B43: # | C43: 0 | D43: 0 | E43: 0 | F43: 0 | G43: 0 | H43: 0 | I43: 0 | J43: 0 | K43: 0 | L43: 0 | M43: 0 | N43: 0 | O43: 0 | P43: 0 | Q43: 0 | R43: 0 | S43: =S15 -> 37.396034 | T43: =S43*(1-Assumptions!$F$27) -> 35.152272 | U43: =T43*(1-Assumptions!$F$27) -> 33.043135 | V43: =U43*(1-Assumptions!$F$27) -> 31.060547 | W43: =V43*(1-Assumptions!$F$27) -> 29.196914 | X43: =W43*(1-Assumptions!$F$27) -> 27.4451 | Y43: =X43*(1-Assumptions!$F$27) -> 25.798394 | Z43: =Y43*(1-Assumptions!$F$27) -> 24.25049 | AA43: =Z43*(1-Assumptions!$F$27) -> 22.795461 | ... AL43: =AK43*(1-Assumptions!$F$27) -> 11.541301
A44: Cohort M18 | B44: # | C44: 0 | D44: 0 | E44: 0 | F44: 0 | G44: 0 | H44: 0 | I44: 0 | J44: 0 | K44: 0 | L44: 0 | M44: 0 | N44: 0 | O44: 0 | P44: 0 | Q44: 0 | R44: 0 | S44: 0 | T44: =T15 -> 41.278952 | U44: =T44*(1-Assumptions!$F$27) -> 38.802215 | V44: =U44*(1-Assumptions!$F$27) -> 36.474082 | W44: =V44*(1-Assumptions!$F$27) -> 34.285637 | X44: =W44*(1-Assumptions!$F$27) -> 32.228499 | Y44: =X44*(1-Assumptions!$F$27) -> 30.294789 | Z44: =Y44*(1-Assumptions!$F$27) -> 28.477102 | AA44: =Z44*(1-Assumptions!$F$27) -> 26.768476 | AB44: =AA44*(1-Assumptions!$F$27) -> 25.162367 | ... AL44: =AK44*(1-Assumptions!$F$27) -> 13.552831
A45: Cohort M19 | B45: # | C45: 0 | D45: 0 | E45: 0 | F45: 0 | G45: 0 | H45: 0 | I45: 0 | J45: 0 | K45: 0 | L45: 0 | M45: 0 | N45: 0 | O45: 0 | P45: 0 | Q45: 0 | R45: 0 | S45: 0 | T45: 0 | U45: =U15 -> 45.577755 | V45: =U45*(1-Assumptions!$F$27) -> 42.84309 | W45: =V45*(1-Assumptions!$F$27) -> 40.272504 | X45: =W45*(1-Assumptions!$F$27) -> 37.856154 | Y45: =X45*(1-Assumptions!$F$27) -> 35.584785 | Z45: =Y45*(1-Assumptions!$F$27) -> 33.449698 | AA45: =Z45*(1-Assumptions!$F$27) -> 31.442716 | AB45: =AA45*(1-Assumptions!$F$27) -> 29.556153 | AC45: =AB45*(1-Assumptions!$F$27) -> 27.782784 | ... AL45: =AK45*(1-Assumptions!$F$27) -> 15.919391
A46: Cohort M20 | B46: # | C46: 0 | D46: 0 | E46: 0 | F46: 0 | G46: 0 | H46: 0 | I46: 0 | J46: 0 | K46: 0 | L46: 0 | M46: 0 | N46: 0 | O46: 0 | P46: 0 | Q46: 0 | R46: 0 | S46: 0 | T46: 0 | U46: 0 | V46: =V15 -> 50.338417 | W46: =V46*(1-Assumptions!$F$27) -> 47.318112 | X46: =W46*(1-Assumptions!$F$27) -> 44.479026 | Y46: =X46*(1-Assumptions!$F$27) -> 41.810284 | Z46: =Y46*(1-Assumptions!$F$27) -> 39.301667 | AA46: =Z46*(1-Assumptions!$F$27) -> 36.943567 | AB46: =AA46*(1-Assumptions!$F$27) -> 34.726953 | AC46: =AB46*(1-Assumptions!$F$27) -> 32.643336 | AD46: =AC46*(1-Assumptions!$F$27) -> 30.684736 | ... AL46: =AK46*(1-Assumptions!$F$27) -> 18.704462
A47: Cohort M21 | B47: # | C47: 0 | D47: 0 | E47: 0 | F47: 0 | G47: 0 | H47: 0 | I47: 0 | J47: 0 | K47: 0 | L47: 0 | M47: 0 | N47: 0 | O47: 0 | P47: 0 | Q47: 0 | R47: 0 | S47: 0 | T47: 0 | U47: 0 | V47: 0 | W47: =W15 -> 55.612111 | X47: =W47*(1-Assumptions!$F$27) -> 52.275385 | Y47: =X47*(1-Assumptions!$F$27) -> 49.138862 | Z47: =Y47*(1-Assumptions!$F$27) -> 46.19053 | AA47: =Z47*(1-Assumptions!$F$27) -> 43.419098 | AB47: =AA47*(1-Assumptions!$F$27) -> 40.813952 | AC47: =AB47*(1-Assumptions!$F$27) -> 38.365115 | AD47: =AC47*(1-Assumptions!$F$27) -> 36.063208 | AE47: =AD47*(1-Assumptions!$F$27) -> 33.899416 | ... AL47: =AK47*(1-Assumptions!$F$27) -> 21.983012
A48: Cohort M22 | B48: # | C48: 0 | D48: 0 | E48: 0 | F48: 0 | G48: 0 | H48: 0 | I48: 0 | J48: 0 | K48: 0 | L48: 0 | M48: 0 | N48: 0 | O48: 0 | P48: 0 | Q48: 0 | R48: 0 | S48: 0 | T48: 0 | U48: 0 | V48: 0 | W48: 0 | X48: =X15 -> 61.455807 | Y48: =X48*(1-Assumptions!$F$27) -> 57.768458 | Z48: =Y48*(1-Assumptions!$F$27) -> 54.302351 | AA48: =Z48*(1-Assumptions!$F$27) -> 51.04421 | AB48: =AA48*(1-Assumptions!$F$27) -> 47.981557 | AC48: =AB48*(1-Assumptions!$F$27) -> 45.102664 | AD48: =AC48*(1-Assumptions!$F$27) -> 42.396504 | AE48: =AD48*(1-Assumptions!$F$27) -> 39.852714 | AF48: =AE48*(1-Assumptions!$F$27) -> 37.461551 | ... AL48: =AK48*(1-Assumptions!$F$27) -> 25.843592
A49: Cohort M23 | B49: # | C49: 0 | D49: 0 | E49: 0 | F49: 0 | G49: 0 | H49: 0 | I49: 0 | J49: 0 | K49: 0 | L49: 0 | M49: 0 | N49: 0 | O49: 0 | P49: 0 | Q49: 0 | R49: 0 | S49: 0 | T49: 0 | U49: 0 | V49: 0 | W49: 0 | X49: 0 | Y49: =Y15 -> 67.932937 | Z49: =Y49*(1-Assumptions!$F$27) -> 63.856961 | AA49: =Z49*(1-Assumptions!$F$27) -> 60.025543 | AB49: =AA49*(1-Assumptions!$F$27) -> 56.424011 | AC49: =AB49*(1-Assumptions!$F$27) -> 53.03857 | AD49: =AC49*(1-Assumptions!$F$27) -> 49.856256 | AE49: =AD49*(1-Assumptions!$F$27) -> 46.86488 | AF49: =AE49*(1-Assumptions!$F$27) -> 44.052988 | AG49: =AF49*(1-Assumptions!$F$27) -> 41.409808 | ... AL49: =AK49*(1-Assumptions!$F$27) -> 30.390825
A50: Cohort M24 | B50: # | C50: 0 | D50: 0 | E50: 0 | F50: 0 | G50: 0 | H50: 0 | I50: 0 | J50: 0 | K50: 0 | L50: 0 | M50: 0 | N50: 0 | O50: 0 | P50: 0 | Q50: 0 | R50: 0 | S50: 0 | T50: 0 | U50: 0 | V50: 0 | W50: 0 | X50: 0 | Y50: 0 | Z50: =Z15 -> 75.114148 | AA50: =Z50*(1-Assumptions!$F$27) -> 70.6073 | AB50: =AA50*(1-Assumptions!$F$27) -> 66.370862 | AC50: =AB50*(1-Assumptions!$F$27) -> 62.38861 | AD50: =AC50*(1-Assumptions!$F$27) -> 58.645293 | AE50: =AD50*(1-Assumptions!$F$27) -> 55.126576 | AF50: =AE50*(1-Assumptions!$F$27) -> 51.818981 | AG50: =AF50*(1-Assumptions!$F$27) -> 48.709842 | AH50: =AG50*(1-Assumptions!$F$27) -> 45.787252 | ... AL50: =AK50*(1-Assumptions!$F$27) -> 35.748349
A51: Cohort M25 | B51: # | C51: 0 | D51: 0 | E51: 0 | F51: 0 | G51: 0 | H51: 0 | I51: 0 | J51: 0 | K51: 0 | L51: 0 | M51: 0 | N51: 0 | O51: 0 | P51: 0 | Q51: 0 | R51: 0 | S51: 0 | T51: 0 | U51: 0 | V51: 0 | W51: 0 | X51: 0 | Y51: 0 | Z51: 0 | AA51: =AA15 -> 83.078131 | AB51: =AA51*(1-Assumptions!$F$27) -> 78.093443 | AC51: =AB51*(1-Assumptions!$F$27) -> 73.407837 | AD51: =AC51*(1-Assumptions!$F$27) -> 69.003367 | AE51: =AD51*(1-Assumptions!$F$27) -> 64.863165 | AF51: =AE51*(1-Assumptions!$F$27) -> 60.971375 | AG51: =AF51*(1-Assumptions!$F$27) -> 57.313092 | AH51: =AG51*(1-Assumptions!$F$27) -> 53.874307 | AI51: =AH51*(1-Assumptions!$F$27) -> 50.641848 | ... AL51: =AK51*(1-Assumptions!$F$27) -> 42.062309
A52: Cohort M26 | B52: # | C52: 0 | D52: 0 | E52: 0 | F52: 0 | G52: 0 | H52: 0 | I52: 0 | J52: 0 | K52: 0 | L52: 0 | M52: 0 | N52: 0 | O52: 0 | P52: 0 | Q52: 0 | R52: 0 | S52: 0 | T52: 0 | U52: 0 | V52: 0 | W52: 0 | X52: 0 | Y52: 0 | Z52: 0 | AA52: 0 | AB52: =AB15 -> 91.911454 | AC52: =AB52*(1-Assumptions!$F$27) -> 86.396767 | AD52: =AC52*(1-Assumptions!$F$27) -> 81.212961 | AE52: =AD52*(1-Assumptions!$F$27) -> 76.340183 | AF52: =AE52*(1-Assumptions!$F$27) -> 71.759772 | AG52: =AF52*(1-Assumptions!$F$27) -> 67.454186 | AH52: =AG52*(1-Assumptions!$F$27) -> 63.406935 | AI52: =AH52*(1-Assumptions!$F$27) -> 59.602519 | AJ52: =AI52*(1-Assumptions!$F$27) -> 56.026368 | ... AL52: =AK52*(1-Assumptions!$F$27) -> 49.504898
A53: Cohort M27 | B53: # | C53: 0 | D53: 0 | E53: 0 | F53: 0 | G53: 0 | H53: 0 | I53: 0 | J53: 0 | K53: 0 | L53: 0 | M53: 0 | N53: 0 | O53: 0 | P53: 0 | Q53: 0 | R53: 0 | S53: 0 | T53: 0 | U53: 0 | V53: 0 | W53: 0 | X53: 0 | Y53: 0 | Z53: 0 | AA53: 0 | AB53: 0 | AC53: =AC15 -> 101.71278 | AD53: =AC53*(1-Assumptions!$F$27) -> 95.610015 | AE53: =AD53*(1-Assumptions!$F$27) -> 89.873414 | AF53: =AE53*(1-Assumptions!$F$27) -> 84.481009 | AG53: =AF53*(1-Assumptions!$F$27) -> 79.412149 | AH53: =AG53*(1-Assumptions!$F$27) -> 74.64742 | AI53: =AH53*(1-Assumptions!$F$27) -> 70.168575 | AJ53: =AI53*(1-Assumptions!$F$27) -> 65.95846 | AK53: =AJ53*(1-Assumptions!$F$27) -> 62.000953 | AL53: =AK53*(1-Assumptions!$F$27) -> 58.280895
A54: Cohort M28 | B54: # | C54: 0 | D54: 0 | E54: 0 | F54: 0 | G54: 0 | H54: 0 | I54: 0 | J54: 0 | K54: 0 | L54: 0 | M54: 0 | N54: 0 | O54: 0 | P54: 0 | Q54: 0 | R54: 0 | S54: 0 | T54: 0 | U54: 0 | V54: 0 | W54: 0 | X54: 0 | Y54: 0 | Z54: 0 | AA54: 0 | AB54: 0 | AC54: 0 | AD54: =AD15 -> 107.92738 | AE54: =AD54*(1-Assumptions!$F$27) -> 101.45174 | AF54: =AE54*(1-Assumptions!$F$27) -> 95.364635 | AG54: =AF54*(1-Assumptions!$F$27) -> 89.642757 | AH54: =AG54*(1-Assumptions!$F$27) -> 84.264192 | AI54: =AH54*(1-Assumptions!$F$27) -> 79.20834 | AJ54: =AI54*(1-Assumptions!$F$27) -> 74.45584 | AK54: =AJ54*(1-Assumptions!$F$27) -> 69.988489 | AL54: =AK54*(1-Assumptions!$F$27) -> 65.78918
A55: Cohort M29 | B55: # | C55: 0 | D55: 0 | E55: 0 | F55: 0 | G55: 0 | H55: 0 | I55: 0 | J55: 0 | K55: 0 | L55: 0 | M55: 0 | N55: 0 | O55: 0 | P55: 0 | Q55: 0 | R55: 0 | S55: 0 | T55: 0 | U55: 0 | V55: 0 | W55: 0 | X55: 0 | Y55: 0 | Z55: 0 | AA55: 0 | AB55: 0 | AC55: 0 | AD55: 0 | AE55: =AE15 -> 110.98072 | AF55: =AE55*(1-Assumptions!$F$27) -> 104.32188 | AG55: =AF55*(1-Assumptions!$F$27) -> 98.062563 | AH55: =AG55*(1-Assumptions!$F$27) -> 92.17881 | AI55: =AH55*(1-Assumptions!$F$27) -> 86.648081 | AJ55: =AI55*(1-Assumptions!$F$27) -> 81.449196 | AK55: =AJ55*(1-Assumptions!$F$27) -> 76.562244 | AL55: =AK55*(1-Assumptions!$F$27) -> 71.96851
A56: Cohort M30 | B56: # | C56: 0 | D56: 0 | E56: 0 | F56: 0 | G56: 0 | H56: 0 | I56: 0 | J56: 0 | K56: 0 | L56: 0 | M56: 0 | N56: 0 | O56: 0 | P56: 0 | Q56: 0 | R56: 0 | S56: 0 | T56: 0 | U56: 0 | V56: 0 | W56: 0 | X56: 0 | Y56: 0 | Z56: 0 | AA56: 0 | AB56: 0 | AC56: 0 | AD56: 0 | AE56: 0 | AF56: =AF15 -> 114.25752 | AG56: =AF56*(1-Assumptions!$F$27) -> 107.40207 | AH56: =AG56*(1-Assumptions!$F$27) -> 100.95795 | AI56: =AH56*(1-Assumptions!$F$27) -> 94.900471 | AJ56: =AI56*(1-Assumptions!$F$27) -> 89.206443 | AK56: =AJ56*(1-Assumptions!$F$27) -> 83.854056 | AL56: =AK56*(1-Assumptions!$F$27) -> 78.822813
A57: Cohort M31 | B57: # | C57: 0 | D57: 0 | E57: 0 | F57: 0 | G57: 0 | H57: 0 | I57: 0 | J57: 0 | K57: 0 | L57: 0 | M57: 0 | N57: 0 | O57: 0 | P57: 0 | Q57: 0 | R57: 0 | S57: 0 | T57: 0 | U57: 0 | V57: 0 | W57: 0 | X57: 0 | Y57: 0 | Z57: 0 | AA57: 0 | AB57: 0 | AC57: 0 | AD57: 0 | AE57: 0 | AF57: 0 | AG57: =AG15 -> 117.7766 | AH57: =AG57*(1-Assumptions!$F$27) -> 110.71 | AI57: =AH57*(1-Assumptions!$F$27) -> 104.0674 | AJ57: =AI57*(1-Assumptions!$F$27) -> 97.823359 | AK57: =AJ57*(1-Assumptions!$F$27) -> 91.953958 | AL57: =AK57*(1-Assumptions!$F$27) -> 86.43672
A58: Cohort M32 | B58: # | C58: 0 | D58: 0 | E58: 0 | F58: 0 | G58: 0 | H58: 0 | I58: 0 | J58: 0 | K58: 0 | L58: 0 | M58: 0 | N58: 0 | O58: 0 | P58: 0 | Q58: 0 | R58: 0 | S58: 0 | T58: 0 | U58: 0 | V58: 0 | W58: 0 | X58: 0 | Y58: 0 | Z58: 0 | AA58: 0 | AB58: 0 | AC58: 0 | AD58: 0 | AE58: 0 | AF58: 0 | AG58: 0 | AH58: =AH15 -> 121.5582 | AI58: =AH58*(1-Assumptions!$F$27) -> 114.2647 | AJ58: =AI58*(1-Assumptions!$F$27) -> 107.40882 | AK58: =AJ58*(1-Assumptions!$F$27) -> 100.96429 | AL58: =AK58*(1-Assumptions!$F$27) -> 94.906435
A59: Cohort M33 | B59: # | C59: 0 | D59: 0 | E59: 0 | F59: 0 | G59: 0 | H59: 0 | I59: 0 | J59: 0 | K59: 0 | L59: 0 | M59: 0 | N59: 0 | O59: 0 | P59: 0 | Q59: 0 | R59: 0 | S59: 0 | T59: 0 | U59: 0 | V59: 0 | W59: 0 | X59: 0 | Y59: 0 | Z59: 0 | AA59: 0 | AB59: 0 | AC59: 0 | AD59: 0 | AE59: 0 | AF59: 0 | AG59: 0 | AH59: 0 | AI59: =AI15 -> 125.62413 | AJ59: =AI59*(1-Assumptions!$F$27) -> 118.08668 | AK59: =AJ59*(1-Assumptions!$F$27) -> 111.00148 | AL59: =AK59*(1-Assumptions!$F$27) -> 104.34139
A60: Cohort M34 | B60: # | C60: 0 | D60: 0 | E60: 0 | F60: 0 | G60: 0 | H60: 0 | I60: 0 | J60: 0 | K60: 0 | L60: 0 | M60: 0 | N60: 0 | O60: 0 | P60: 0 | Q60: 0 | R60: 0 | S60: 0 | T60: 0 | U60: 0 | V60: 0 | W60: 0 | X60: 0 | Y60: 0 | Z60: 0 | AA60: 0 | AB60: 0 | AC60: 0 | AD60: 0 | AE60: 0 | AF60: 0 | AG60: 0 | AH60: 0 | AI60: 0 | AJ60: =AJ15 -> 127.02328 | AK60: =AJ60*(1-Assumptions!$F$27) -> 119.40189 | AL60: =AK60*(1-Assumptions!$F$27) -> 112.23777
A61: Cohort M35 | B61: # | C61: 0 | D61: 0 | E61: 0 | F61: 0 | G61: 0 | H61: 0 | I61: 0 | J61: 0 | K61: 0 | L61: 0 | M61: 0 | N61: 0 | O61: 0 | P61: 0 | Q61: 0 | R61: 0 | S61: 0 | T61: 0 | U61: 0 | V61: 0 | W61: 0 | X61: 0 | Y61: 0 | Z61: 0 | AA61: 0 | AB61: 0 | AC61: 0 | AD61: 0 | AE61: 0 | AF61: 0 | AG61: 0 | AH61: 0 | AI61: 0 | AJ61: 0 | AK61: =AK15 -> 127.25846 | AL61: =AK61*(1-Assumptions!$F$27) -> 119.62295
A62: Cohort M36 | B62: # | C62: 0 | D62: 0 | E62: 0 | F62: 0 | G62: 0 | H62: 0 | I62: 0 | J62: 0 | K62: 0 | L62: 0 | M62: 0 | N62: 0 | O62: 0 | P62: 0 | Q62: 0 | R62: 0 | S62: 0 | T62: 0 | U62: 0 | V62: 0 | W62: 0 | X62: 0 | Y62: 0 | Z62: 0 | AA62: 0 | AB62: 0 | AC62: 0 | AD62: 0 | AE62: 0 | AF62: 0 | AG62: 0 | AH62: 0 | AI62: 0 | AJ62: 0 | AK62: 0 | AL62: =AL15 -> 127.48289
A64: COHORT WATERFALL — ANNUAL PLAN (active customers)
A65: Cohort ↓ / Month → | B65: # | C65: 1 | D65: 2 | E65: 3 | F65: 4 | G65: 5 | H65: 6 | I65: 7 | J65: 8 | K65: 9 | L65: 10 | M65: 11 | N65: 12 | O65: 13 | P65: 14 | Q65: 15 | R65: 16 | S65: 17 | T65: 18 | U65: 19 | V65: 20 | W65: 21 | X65: 22 | Y65: 23 | Z65: 24 | AA65: 25 | AB65: 26 | AC65: 27 | AD65: 28 | AE65: 29 | AF65: 30 | AG65: 31 | AH65: 32 | AI65: 33 | AJ65: 34 | AK65: 35 | AL65: 36
A66: Cohort M1 | B66: # | C66: =C16 -> 1.98 | D66: =C66 -> 1.98 | E66: =D66 -> 1.98 | F66: =E66 -> 1.98 | G66: =F66 -> 1.98 | H66: =G66 -> 1.98 | I66: =H66 -> 1.98 | J66: =I66 -> 1.98 | K66: =J66 -> 1.98 | ... N66: =M66 -> 1.98 | O66: =N66*Assumptions!$F$28 -> 1.386 | P66: =O66 -> 1.386 | Q66: =P66 -> 1.386 | R66: =Q66 -> 1.386 | S66: =R66 -> 1.386 | T66: =S66 -> 1.386 | U66: =T66 -> 1.386 | V66: =U66 -> 1.386 | W66: =V66 -> 1.386 | ... Z66: =Y66 -> 1.386 | AA66: =Z66*Assumptions!$F$28 -> 0.9702 | AB66: =AA66 -> 0.9702 | AC66: =AB66 -> 0.9702 | AD66: =AC66 -> 0.9702 | AE66: =AD66 -> 0.9702 | AF66: =AE66 -> 0.9702 | AG66: =AF66 -> 0.9702 | AH66: =AG66 -> 0.9702 | AI66: =AH66 -> 0.9702 | ... AL66: =AK66 -> 0.9702
A67: Cohort M2 | B67: # | C67: 0 | D67: =D16 -> 2.180134 | E67: =D67 -> 2.180134 | F67: =E67 -> 2.180134 | G67: =F67 -> 2.180134 | H67: =G67 -> 2.180134 | I67: =H67 -> 2.180134 | J67: =I67 -> 2.180134 | K67: =J67 -> 2.180134 | L67: =K67 -> 2.180134 | ... O67: =N67 -> 2.180134 | P67: =O67*Assumptions!$F$28 -> 1.5260938 | Q67: =P67 -> 1.5260938 | R67: =Q67 -> 1.5260938 | S67: =R67 -> 1.5260938 | T67: =S67 -> 1.5260938 | U67: =T67 -> 1.5260938 | V67: =U67 -> 1.5260938 | W67: =V67 -> 1.5260938 | X67: =W67 -> 1.5260938 | ... AA67: =Z67 -> 1.5260938 | AB67: =AA67*Assumptions!$F$28 -> 1.0682657 | AC67: =AB67 -> 1.0682657 | AD67: =AC67 -> 1.0682657 | AE67: =AD67 -> 1.0682657 | AF67: =AE67 -> 1.0682657 | AG67: =AF67 -> 1.0682657 | AH67: =AG67 -> 1.0682657 | AI67: =AH67 -> 1.0682657 | AJ67: =AI67 -> 1.0682657 | ... AL67: =AK67 -> 1.0682657
A68: Cohort M3 | B68: # | C68: 0 | D68: 0 | E68: =E16 -> 2.4003268 | F68: =E68 -> 2.4003268 | G68: =F68 -> 2.4003268 | H68: =G68 -> 2.4003268 | I68: =H68 -> 2.4003268 | J68: =I68 -> 2.4003268 | K68: =J68 -> 2.4003268 | L68: =K68 -> 2.4003268 | M68: =L68 -> 2.4003268 | ... P68: =O68 -> 2.4003268 | Q68: =P68*Assumptions!$F$28 -> 1.6802288 | R68: =Q68 -> 1.6802288 | S68: =R68 -> 1.6802288 | T68: =S68 -> 1.6802288 | U68: =T68 -> 1.6802288 | V68: =U68 -> 1.6802288 | W68: =V68 -> 1.6802288 | X68: =W68 -> 1.6802288 | Y68: =X68 -> 1.6802288 | ... AB68: =AA68 -> 1.6802288 | AC68: =AB68*Assumptions!$F$28 -> 1.1761601 | AD68: =AC68 -> 1.1761601 | AE68: =AD68 -> 1.1761601 | AF68: =AE68 -> 1.1761601 | AG68: =AF68 -> 1.1761601 | AH68: =AG68 -> 1.1761601 | AI68: =AH68 -> 1.1761601 | AJ68: =AI68 -> 1.1761601 | AK68: =AJ68 -> 1.1761601 | AL68: =AK68 -> 1.1761601
A69: Cohort M4 | B69: # | C69: 0 | D69: 0 | E69: 0 | F69: =F16 -> 2.6427156 | G69: =F69 -> 2.6427156 | H69: =G69 -> 2.6427156 | I69: =H69 -> 2.6427156 | J69: =I69 -> 2.6427156 | K69: =J69 -> 2.6427156 | L69: =K69 -> 2.6427156 | M69: =L69 -> 2.6427156 | N69: =M69 -> 2.6427156 | ... Q69: =P69 -> 2.6427156 | R69: =Q69*Assumptions!$F$28 -> 1.8499009 | S69: =R69 -> 1.8499009 | T69: =S69 -> 1.8499009 | U69: =T69 -> 1.8499009 | V69: =U69 -> 1.8499009 | W69: =V69 -> 1.8499009 | X69: =W69 -> 1.8499009 | Y69: =X69 -> 1.8499009 | Z69: =Y69 -> 1.8499009 | ... AC69: =AB69 -> 1.8499009 | AD69: =AC69*Assumptions!$F$28 -> 1.2949306 | AE69: =AD69 -> 1.2949306 | AF69: =AE69 -> 1.2949306 | AG69: =AF69 -> 1.2949306 | AH69: =AG69 -> 1.2949306 | AI69: =AH69 -> 1.2949306 | AJ69: =AI69 -> 1.2949306 | AK69: =AJ69 -> 1.2949306 | AL69: =AK69 -> 1.2949306
A70: Cohort M5 | B70: # | C70: 0 | D70: 0 | E70: 0 | F70: 0 | G70: =G16 -> 2.9096696 | H70: =G70 -> 2.9096696 | I70: =H70 -> 2.9096696 | J70: =I70 -> 2.9096696 | K70: =J70 -> 2.9096696 | L70: =K70 -> 2.9096696 | M70: =L70 -> 2.9096696 | N70: =M70 -> 2.9096696 | O70: =N70 -> 2.9096696 | ... R70: =Q70 -> 2.9096696 | S70: =R70*Assumptions!$F$28 -> 2.0367688 | T70: =S70 -> 2.0367688 | U70: =T70 -> 2.0367688 | V70: =U70 -> 2.0367688 | W70: =V70 -> 2.0367688 | X70: =W70 -> 2.0367688 | Y70: =X70 -> 2.0367688 | Z70: =Y70 -> 2.0367688 | AA70: =Z70 -> 2.0367688 | ... AD70: =AC70 -> 2.0367688 | AE70: =AD70*Assumptions!$F$28 -> 1.4257381 | AF70: =AE70 -> 1.4257381 | AG70: =AF70 -> 1.4257381 | AH70: =AG70 -> 1.4257381 | AI70: =AH70 -> 1.4257381 | AJ70: =AI70 -> 1.4257381 | AK70: =AJ70 -> 1.4257381 | AL70: =AK70 -> 1.4257381
A71: Cohort M6 | B71: # | C71: 0 | D71: 0 | E71: 0 | F71: 0 | G71: 0 | H71: =H16 -> 3.2038166 | I71: =H71 -> 3.2038166 | J71: =I71 -> 3.2038166 | K71: =J71 -> 3.2038166 | L71: =K71 -> 3.2038166 | M71: =L71 -> 3.2038166 | N71: =M71 -> 3.2038166 | O71: =N71 -> 3.2038166 | P71: =O71 -> 3.2038166 | ... S71: =R71 -> 3.2038166 | T71: =S71*Assumptions!$F$28 -> 2.2426716 | U71: =T71 -> 2.2426716 | V71: =U71 -> 2.2426716 | W71: =V71 -> 2.2426716 | X71: =W71 -> 2.2426716 | Y71: =X71 -> 2.2426716 | Z71: =Y71 -> 2.2426716 | AA71: =Z71 -> 2.2426716 | AB71: =AA71 -> 2.2426716 | ... AE71: =AD71 -> 2.2426716 | AF71: =AE71*Assumptions!$F$28 -> 1.5698701 | AG71: =AF71 -> 1.5698701 | AH71: =AG71 -> 1.5698701 | AI71: =AH71 -> 1.5698701 | AJ71: =AI71 -> 1.5698701 | AK71: =AJ71 -> 1.5698701 | AL71: =AK71 -> 1.5698701
A72: Cohort M7 | B72: # | C72: 0 | D72: 0 | E72: 0 | F72: 0 | G72: 0 | H72: 0 | I72: =I16 -> 3.5280713 | J72: =I72 -> 3.5280713 | K72: =J72 -> 3.5280713 | L72: =K72 -> 3.5280713 | M72: =L72 -> 3.5280713 | N72: =M72 -> 3.5280713 | O72: =N72 -> 3.5280713 | P72: =O72 -> 3.5280713 | Q72: =P72 -> 3.5280713 | ... T72: =S72 -> 3.5280713 | U72: =T72*Assumptions!$F$28 -> 2.4696499 | V72: =U72 -> 2.4696499 | W72: =V72 -> 2.4696499 | X72: =W72 -> 2.4696499 | Y72: =X72 -> 2.4696499 | Z72: =Y72 -> 2.4696499 | AA72: =Z72 -> 2.4696499 | AB72: =AA72 -> 2.4696499 | AC72: =AB72 -> 2.4696499 | ... AF72: =AE72 -> 2.4696499 | AG72: =AF72*Assumptions!$F$28 -> 1.7287549 | AH72: =AG72 -> 1.7287549 | AI72: =AH72 -> 1.7287549 | AJ72: =AI72 -> 1.7287549 | AK72: =AJ72 -> 1.7287549 | AL72: =AK72 -> 1.7287549
A73: Cohort M8 | B73: # | C73: 0 | D73: 0 | E73: 0 | F73: 0 | G73: 0 | H73: 0 | I73: 0 | J73: =J16 -> 3.8856684 | K73: =J73 -> 3.8856684 | L73: =K73 -> 3.8856684 | M73: =L73 -> 3.8856684 | N73: =M73 -> 3.8856684 | O73: =N73 -> 3.8856684 | P73: =O73 -> 3.8856684 | Q73: =P73 -> 3.8856684 | R73: =Q73 -> 3.8856684 | ... U73: =T73 -> 3.8856684 | V73: =U73*Assumptions!$F$28 -> 2.7199679 | W73: =V73 -> 2.7199679 | X73: =W73 -> 2.7199679 | Y73: =X73 -> 2.7199679 | Z73: =Y73 -> 2.7199679 | AA73: =Z73 -> 2.7199679 | AB73: =AA73 -> 2.7199679 | AC73: =AB73 -> 2.7199679 | AD73: =AC73 -> 2.7199679 | ... AG73: =AF73 -> 2.7199679 | AH73: =AG73*Assumptions!$F$28 -> 1.9039775 | AI73: =AH73 -> 1.9039775 | AJ73: =AI73 -> 1.9039775 | AK73: =AJ73 -> 1.9039775 | AL73: =AK73 -> 1.9039775
A74: Cohort M9 | B74: # | C74: 0 | D74: 0 | E74: 0 | F74: 0 | G74: 0 | H74: 0 | I74: 0 | J74: 0 | K74: =K16 -> 4.2801981 | L74: =K74 -> 4.2801981 | M74: =L74 -> 4.2801981 | N74: =M74 -> 4.2801981 | O74: =N74 -> 4.2801981 | P74: =O74 -> 4.2801981 | Q74: =P74 -> 4.2801981 | R74: =Q74 -> 4.2801981 | S74: =R74 -> 4.2801981 | ... V74: =U74 -> 4.2801981 | W74: =V74*Assumptions!$F$28 -> 2.9961387 | X74: =W74 -> 2.9961387 | Y74: =X74 -> 2.9961387 | Z74: =Y74 -> 2.9961387 | AA74: =Z74 -> 2.9961387 | AB74: =AA74 -> 2.9961387 | AC74: =AB74 -> 2.9961387 | AD74: =AC74 -> 2.9961387 | AE74: =AD74 -> 2.9961387 | ... AH74: =AG74 -> 2.9961387 | AI74: =AH74*Assumptions!$F$28 -> 2.0972971 | AJ74: =AI74 -> 2.0972971 | AK74: =AJ74 -> 2.0972971 | AL74: =AK74 -> 2.0972971
A75: Cohort M10 | B75: # | C75: 0 | D75: 0 | E75: 0 | F75: 0 | G75: 0 | H75: 0 | I75: 0 | J75: 0 | K75: 0 | L75: =L16 -> 4.7156468 | M75: =L75 -> 4.7156468 | N75: =M75 -> 4.7156468 | O75: =N75 -> 4.7156468 | P75: =O75 -> 4.7156468 | Q75: =P75 -> 4.7156468 | R75: =Q75 -> 4.7156468 | S75: =R75 -> 4.7156468 | T75: =S75 -> 4.7156468 | ... W75: =V75 -> 4.7156468 | X75: =W75*Assumptions!$F$28 -> 3.3009528 | Y75: =X75 -> 3.3009528 | Z75: =Y75 -> 3.3009528 | AA75: =Z75 -> 3.3009528 | AB75: =AA75 -> 3.3009528 | AC75: =AB75 -> 3.3009528 | AD75: =AC75 -> 3.3009528 | AE75: =AD75 -> 3.3009528 | AF75: =AE75 -> 3.3009528 | ... AI75: =AH75 -> 3.3009528 | AJ75: =AI75*Assumptions!$F$28 -> 2.3106669 | AK75: =AJ75 -> 2.3106669 | AL75: =AK75 -> 2.3106669
A76: Cohort M11 | B76: # | C76: 0 | D76: 0 | E76: 0 | F76: 0 | G76: 0 | H76: 0 | I76: 0 | J76: 0 | K76: 0 | L76: 0 | M76: =M16 -> 5.1964416 | N76: =M76 -> 5.1964416 | O76: =N76 -> 5.1964416 | P76: =O76 -> 5.1964416 | Q76: =P76 -> 5.1964416 | R76: =Q76 -> 5.1964416 | S76: =R76 -> 5.1964416 | T76: =S76 -> 5.1964416 | U76: =T76 -> 5.1964416 | ... X76: =W76 -> 5.1964416 | Y76: =X76*Assumptions!$F$28 -> 3.6375091 | Z76: =Y76 -> 3.6375091 | AA76: =Z76 -> 3.6375091 | AB76: =AA76 -> 3.6375091 | AC76: =AB76 -> 3.6375091 | AD76: =AC76 -> 3.6375091 | AE76: =AD76 -> 3.6375091 | AF76: =AE76 -> 3.6375091 | AG76: =AF76 -> 3.6375091 | ... AJ76: =AI76 -> 3.6375091 | AK76: =AJ76*Assumptions!$F$28 -> 2.5462564 | AL76: =AK76 -> 2.5462564
A77: Cohort M12 | B77: # | C77: 0 | D77: 0 | E77: 0 | F77: 0 | G77: 0 | H77: 0 | I77: 0 | J77: 0 | K77: 0 | L77: 0 | M77: 0 | N77: =N16 -> 5.7275006 | O77: =N77 -> 5.7275006 | P77: =O77 -> 5.7275006 | Q77: =P77 -> 5.7275006 | R77: =Q77 -> 5.7275006 | S77: =R77 -> 5.7275006 | T77: =S77 -> 5.7275006 | U77: =T77 -> 5.7275006 | V77: =U77 -> 5.7275006 | ... Y77: =X77 -> 5.7275006 | Z77: =Y77*Assumptions!$F$28 -> 4.0092504 | AA77: =Z77 -> 4.0092504 | AB77: =AA77 -> 4.0092504 | AC77: =AB77 -> 4.0092504 | AD77: =AC77 -> 4.0092504 | AE77: =AD77 -> 4.0092504 | AF77: =AE77 -> 4.0092504 | AG77: =AF77 -> 4.0092504 | AH77: =AG77 -> 4.0092504 | ... AK77: =AJ77 -> 4.0092504 | AL77: =AK77*Assumptions!$F$28 -> 2.8064753
A78: Cohort M13 | B78: # | C78: 0 | D78: 0 | E78: 0 | F78: 0 | G78: 0 | H78: 0 | I78: 0 | J78: 0 | K78: 0 | L78: 0 | M78: 0 | N78: 0 | O78: =O16 -> 6.3142881 | P78: =O78 -> 6.3142881 | Q78: =P78 -> 6.3142881 | R78: =Q78 -> 6.3142881 | S78: =R78 -> 6.3142881 | T78: =S78 -> 6.3142881 | U78: =T78 -> 6.3142881 | V78: =U78 -> 6.3142881 | W78: =V78 -> 6.3142881 | ... Z78: =Y78 -> 6.3142881 | AA78: =Z78*Assumptions!$F$28 -> 4.4200017 | AB78: =AA78 -> 4.4200017 | AC78: =AB78 -> 4.4200017 | AD78: =AC78 -> 4.4200017 | AE78: =AD78 -> 4.4200017 | AF78: =AE78 -> 4.4200017 | AG78: =AF78 -> 4.4200017 | AH78: =AG78 -> 4.4200017 | AI78: =AH78 -> 4.4200017 | ... AL78: =AK78 -> 4.4200017
A79: Cohort M14 | B79: # | C79: 0 | D79: 0 | E79: 0 | F79: 0 | G79: 0 | H79: 0 | I79: 0 | J79: 0 | K79: 0 | L79: 0 | M79: 0 | N79: 0 | O79: 0 | P79: =P16 -> 6.9624857 | Q79: =P79 -> 6.9624857 | R79: =Q79 -> 6.9624857 | S79: =R79 -> 6.9624857 | T79: =S79 -> 6.9624857 | U79: =T79 -> 6.9624857 | V79: =U79 -> 6.9624857 | W79: =V79 -> 6.9624857 | X79: =W79 -> 6.9624857 | ... AA79: =Z79 -> 6.9624857 | AB79: =AA79*Assumptions!$F$28 -> 4.87374 | AC79: =AB79 -> 4.87374 | AD79: =AC79 -> 4.87374 | AE79: =AD79 -> 4.87374 | AF79: =AE79 -> 4.87374 | AG79: =AF79 -> 4.87374 | AH79: =AG79 -> 4.87374 | AI79: =AH79 -> 4.87374 | AJ79: =AI79 -> 4.87374 | ... AL79: =AK79 -> 4.87374
A80: Cohort M15 | B80: # | C80: 0 | D80: 0 | E80: 0 | F80: 0 | G80: 0 | H80: 0 | I80: 0 | J80: 0 | K80: 0 | L80: 0 | M80: 0 | N80: 0 | O80: 0 | P80: 0 | Q80: =Q16 -> 7.6791959 | R80: =Q80 -> 7.6791959 | S80: =R80 -> 7.6791959 | T80: =S80 -> 7.6791959 | U80: =T80 -> 7.6791959 | V80: =U80 -> 7.6791959 | W80: =V80 -> 7.6791959 | X80: =W80 -> 7.6791959 | Y80: =X80 -> 7.6791959 | ... AB80: =AA80 -> 7.6791959 | AC80: =AB80*Assumptions!$F$28 -> 5.3754372 | AD80: =AC80 -> 5.3754372 | AE80: =AD80 -> 5.3754372 | AF80: =AE80 -> 5.3754372 | AG80: =AF80 -> 5.3754372 | AH80: =AG80 -> 5.3754372 | AI80: =AH80 -> 5.3754372 | AJ80: =AI80 -> 5.3754372 | AK80: =AJ80 -> 5.3754372 | AL80: =AK80 -> 5.3754372
A81: Cohort M16 | B81: # | C81: 0 | D81: 0 | E81: 0 | F81: 0 | G81: 0 | H81: 0 | I81: 0 | J81: 0 | K81: 0 | L81: 0 | M81: 0 | N81: 0 | O81: 0 | P81: 0 | Q81: 0 | R81: =R16 -> 8.4719219 | S81: =R81 -> 8.4719219 | T81: =S81 -> 8.4719219 | U81: =T81 -> 8.4719219 | V81: =U81 -> 8.4719219 | W81: =V81 -> 8.4719219 | X81: =W81 -> 8.4719219 | Y81: =X81 -> 8.4719219 | Z81: =Y81 -> 8.4719219 | ... AC81: =AB81 -> 8.4719219 | AD81: =AC81*Assumptions!$F$28 -> 5.9303454 | AE81: =AD81 -> 5.9303454 | AF81: =AE81 -> 5.9303454 | AG81: =AF81 -> 5.9303454 | AH81: =AG81 -> 5.9303454 | AI81: =AH81 -> 5.9303454 | AJ81: =AI81 -> 5.9303454 | AK81: =AJ81 -> 5.9303454 | AL81: =AK81 -> 5.9303454
A82: Cohort M17 | B82: # | C82: 0 | D82: 0 | E82: 0 | F82: 0 | G82: 0 | H82: 0 | I82: 0 | J82: 0 | K82: 0 | L82: 0 | M82: 0 | N82: 0 | O82: 0 | P82: 0 | Q82: 0 | R82: 0 | S82: =S16 -> 9.3490084 | T82: =S82 -> 9.3490084 | U82: =T82 -> 9.3490084 | V82: =U82 -> 9.3490084 | W82: =V82 -> 9.3490084 | X82: =W82 -> 9.3490084 | Y82: =X82 -> 9.3490084 | Z82: =Y82 -> 9.3490084 | AA82: =Z82 -> 9.3490084 | ... AD82: =AC82 -> 9.3490084 | AE82: =AD82*Assumptions!$F$28 -> 6.5443059 | AF82: =AE82 -> 6.5443059 | AG82: =AF82 -> 6.5443059 | AH82: =AG82 -> 6.5443059 | AI82: =AH82 -> 6.5443059 | AJ82: =AI82 -> 6.5443059 | AK82: =AJ82 -> 6.5443059 | AL82: =AK82 -> 6.5443059
A83: Cohort M18 | B83: # | C83: 0 | D83: 0 | E83: 0 | F83: 0 | G83: 0 | H83: 0 | I83: 0 | J83: 0 | K83: 0 | L83: 0 | M83: 0 | N83: 0 | O83: 0 | P83: 0 | Q83: 0 | R83: 0 | S83: 0 | T83: =T16 -> 10.319738 | U83: =T83 -> 10.319738 | V83: =U83 -> 10.319738 | W83: =V83 -> 10.319738 | X83: =W83 -> 10.319738 | Y83: =X83 -> 10.319738 | Z83: =Y83 -> 10.319738 | AA83: =Z83 -> 10.319738 | AB83: =AA83 -> 10.319738 | ... AE83: =AD83 -> 10.319738 | AF83: =AE83*Assumptions!$F$28 -> 7.2238166 | AG83: =AF83 -> 7.2238166 | AH83: =AG83 -> 7.2238166 | AI83: =AH83 -> 7.2238166 | AJ83: =AI83 -> 7.2238166 | AK83: =AJ83 -> 7.2238166 | AL83: =AK83 -> 7.2238166
A84: Cohort M19 | B84: # | C84: 0 | D84: 0 | E84: 0 | F84: 0 | G84: 0 | H84: 0 | I84: 0 | J84: 0 | K84: 0 | L84: 0 | M84: 0 | N84: 0 | O84: 0 | P84: 0 | Q84: 0 | R84: 0 | S84: 0 | T84: 0 | U84: =U16 -> 11.394439 | V84: =U84 -> 11.394439 | W84: =V84 -> 11.394439 | X84: =W84 -> 11.394439 | Y84: =X84 -> 11.394439 | Z84: =Y84 -> 11.394439 | AA84: =Z84 -> 11.394439 | AB84: =AA84 -> 11.394439 | AC84: =AB84 -> 11.394439 | ... AF84: =AE84 -> 11.394439 | AG84: =AF84*Assumptions!$F$28 -> 7.9761072 | AH84: =AG84 -> 7.9761072 | AI84: =AH84 -> 7.9761072 | AJ84: =AI84 -> 7.9761072 | AK84: =AJ84 -> 7.9761072 | AL84: =AK84 -> 7.9761072
A85: Cohort M20 | B85: # | C85: 0 | D85: 0 | E85: 0 | F85: 0 | G85: 0 | H85: 0 | I85: 0 | J85: 0 | K85: 0 | L85: 0 | M85: 0 | N85: 0 | O85: 0 | P85: 0 | Q85: 0 | R85: 0 | S85: 0 | T85: 0 | U85: 0 | V85: =V16 -> 12.584604 | W85: =V85 -> 12.584604 | X85: =W85 -> 12.584604 | Y85: =X85 -> 12.584604 | Z85: =Y85 -> 12.584604 | AA85: =Z85 -> 12.584604 | AB85: =AA85 -> 12.584604 | AC85: =AB85 -> 12.584604 | AD85: =AC85 -> 12.584604 | ... AG85: =AF85 -> 12.584604 | AH85: =AG85*Assumptions!$F$28 -> 8.809223 | AI85: =AH85 -> 8.809223 | AJ85: =AI85 -> 8.809223 | AK85: =AJ85 -> 8.809223 | AL85: =AK85 -> 8.809223
A86: Cohort M21 | B86: # | C86: 0 | D86: 0 | E86: 0 | F86: 0 | G86: 0 | H86: 0 | I86: 0 | J86: 0 | K86: 0 | L86: 0 | M86: 0 | N86: 0 | O86: 0 | P86: 0 | Q86: 0 | R86: 0 | S86: 0 | T86: 0 | U86: 0 | V86: 0 | W86: =W16 -> 13.903028 | X86: =W86 -> 13.903028 | Y86: =X86 -> 13.903028 | Z86: =Y86 -> 13.903028 | AA86: =Z86 -> 13.903028 | AB86: =AA86 -> 13.903028 | AC86: =AB86 -> 13.903028 | AD86: =AC86 -> 13.903028 | AE86: =AD86 -> 13.903028 | ... AH86: =AG86 -> 13.903028 | AI86: =AH86*Assumptions!$F$28 -> 9.7321195 | AJ86: =AI86 -> 9.7321195 | AK86: =AJ86 -> 9.7321195 | AL86: =AK86 -> 9.7321195
A87: Cohort M22 | B87: # | C87: 0 | D87: 0 | E87: 0 | F87: 0 | G87: 0 | H87: 0 | I87: 0 | J87: 0 | K87: 0 | L87: 0 | M87: 0 | N87: 0 | O87: 0 | P87: 0 | Q87: 0 | R87: 0 | S87: 0 | T87: 0 | U87: 0 | V87: 0 | W87: 0 | X87: =X16 -> 15.363952 | Y87: =X87 -> 15.363952 | Z87: =Y87 -> 15.363952 | AA87: =Z87 -> 15.363952 | AB87: =AA87 -> 15.363952 | AC87: =AB87 -> 15.363952 | AD87: =AC87 -> 15.363952 | AE87: =AD87 -> 15.363952 | AF87: =AE87 -> 15.363952 | ... AI87: =AH87 -> 15.363952 | AJ87: =AI87*Assumptions!$F$28 -> 10.754766 | AK87: =AJ87 -> 10.754766 | AL87: =AK87 -> 10.754766
A88: Cohort M23 | B88: # | C88: 0 | D88: 0 | E88: 0 | F88: 0 | G88: 0 | H88: 0 | I88: 0 | J88: 0 | K88: 0 | L88: 0 | M88: 0 | N88: 0 | O88: 0 | P88: 0 | Q88: 0 | R88: 0 | S88: 0 | T88: 0 | U88: 0 | V88: 0 | W88: 0 | X88: 0 | Y88: =Y16 -> 16.983234 | Z88: =Y88 -> 16.983234 | AA88: =Z88 -> 16.983234 | AB88: =AA88 -> 16.983234 | AC88: =AB88 -> 16.983234 | AD88: =AC88 -> 16.983234 | AE88: =AD88 -> 16.983234 | AF88: =AE88 -> 16.983234 | AG88: =AF88 -> 16.983234 | ... AJ88: =AI88 -> 16.983234 | AK88: =AJ88*Assumptions!$F$28 -> 11.888264 | AL88: =AK88 -> 11.888264
A89: Cohort M24 | B89: # | C89: 0 | D89: 0 | E89: 0 | F89: 0 | G89: 0 | H89: 0 | I89: 0 | J89: 0 | K89: 0 | L89: 0 | M89: 0 | N89: 0 | O89: 0 | P89: 0 | Q89: 0 | R89: 0 | S89: 0 | T89: 0 | U89: 0 | V89: 0 | W89: 0 | X89: 0 | Y89: 0 | Z89: =Z16 -> 18.778537 | AA89: =Z89 -> 18.778537 | AB89: =AA89 -> 18.778537 | AC89: =AB89 -> 18.778537 | AD89: =AC89 -> 18.778537 | AE89: =AD89 -> 18.778537 | AF89: =AE89 -> 18.778537 | AG89: =AF89 -> 18.778537 | AH89: =AG89 -> 18.778537 | ... AK89: =AJ89 -> 18.778537 | AL89: =AK89*Assumptions!$F$28 -> 13.144976
A90: Cohort M25 | B90: # | C90: 0 | D90: 0 | E90: 0 | F90: 0 | G90: 0 | H90: 0 | I90: 0 | J90: 0 | K90: 0 | L90: 0 | M90: 0 | N90: 0 | O90: 0 | P90: 0 | Q90: 0 | R90: 0 | S90: 0 | T90: 0 | U90: 0 | V90: 0 | W90: 0 | X90: 0 | Y90: 0 | Z90: 0 | AA90: =AA16 -> 20.769533 | AB90: =AA90 -> 20.769533 | AC90: =AB90 -> 20.769533 | AD90: =AC90 -> 20.769533 | AE90: =AD90 -> 20.769533 | AF90: =AE90 -> 20.769533 | AG90: =AF90 -> 20.769533 | AH90: =AG90 -> 20.769533 | AI90: =AH90 -> 20.769533 | ... AL90: =AK90 -> 20.769533
A91: Cohort M26 | B91: # | C91: 0 | D91: 0 | E91: 0 | F91: 0 | G91: 0 | H91: 0 | I91: 0 | J91: 0 | K91: 0 | L91: 0 | M91: 0 | N91: 0 | O91: 0 | P91: 0 | Q91: 0 | R91: 0 | S91: 0 | T91: 0 | U91: 0 | V91: 0 | W91: 0 | X91: 0 | Y91: 0 | Z91: 0 | AA91: 0 | AB91: =AB16 -> 22.977864 | AC91: =AB91 -> 22.977864 | AD91: =AC91 -> 22.977864 | AE91: =AD91 -> 22.977864 | AF91: =AE91 -> 22.977864 | AG91: =AF91 -> 22.977864 | AH91: =AG91 -> 22.977864 | AI91: =AH91 -> 22.977864 | AJ91: =AI91 -> 22.977864 | ... AL91: =AK91 -> 22.977864
A92: Cohort M27 | B92: # | C92: 0 | D92: 0 | E92: 0 | F92: 0 | G92: 0 | H92: 0 | I92: 0 | J92: 0 | K92: 0 | L92: 0 | M92: 0 | N92: 0 | O92: 0 | P92: 0 | Q92: 0 | R92: 0 | S92: 0 | T92: 0 | U92: 0 | V92: 0 | W92: 0 | X92: 0 | Y92: 0 | Z92: 0 | AA92: 0 | AB92: 0 | AC92: =AC16 -> 25.428196 | AD92: =AC92 -> 25.428196 | AE92: =AD92 -> 25.428196 | AF92: =AE92 -> 25.428196 | AG92: =AF92 -> 25.428196 | AH92: =AG92 -> 25.428196 | AI92: =AH92 -> 25.428196 | AJ92: =AI92 -> 25.428196 | AK92: =AJ92 -> 25.428196 | AL92: =AK92 -> 25.428196
A93: Cohort M28 | B93: # | C93: 0 | D93: 0 | E93: 0 | F93: 0 | G93: 0 | H93: 0 | I93: 0 | J93: 0 | K93: 0 | L93: 0 | M93: 0 | N93: 0 | O93: 0 | P93: 0 | Q93: 0 | R93: 0 | S93: 0 | T93: 0 | U93: 0 | V93: 0 | W93: 0 | X93: 0 | Y93: 0 | Z93: 0 | AA93: 0 | AB93: 0 | AC93: 0 | AD93: =AD16 -> 26.981846 | AE93: =AD93 -> 26.981846 | AF93: =AE93 -> 26.981846 | AG93: =AF93 -> 26.981846 | AH93: =AG93 -> 26.981846 | AI93: =AH93 -> 26.981846 | AJ93: =AI93 -> 26.981846 | AK93: =AJ93 -> 26.981846 | AL93: =AK93 -> 26.981846
A94: Cohort M29 | B94: # | C94: 0 | D94: 0 | E94: 0 | F94: 0 | G94: 0 | H94: 0 | I94: 0 | J94: 0 | K94: 0 | L94: 0 | M94: 0 | N94: 0 | O94: 0 | P94: 0 | Q94: 0 | R94: 0 | S94: 0 | T94: 0 | U94: 0 | V94: 0 | W94: 0 | X94: 0 | Y94: 0 | Z94: 0 | AA94: 0 | AB94: 0 | AC94: 0 | AD94: 0 | AE94: =AE16 -> 27.74518 | AF94: =AE94 -> 27.74518 | AG94: =AF94 -> 27.74518 | AH94: =AG94 -> 27.74518 | AI94: =AH94 -> 27.74518 | AJ94: =AI94 -> 27.74518 | AK94: =AJ94 -> 27.74518 | AL94: =AK94 -> 27.74518
A95: Cohort M30 | B95: # | C95: 0 | D95: 0 | E95: 0 | F95: 0 | G95: 0 | H95: 0 | I95: 0 | J95: 0 | K95: 0 | L95: 0 | M95: 0 | N95: 0 | O95: 0 | P95: 0 | Q95: 0 | R95: 0 | S95: 0 | T95: 0 | U95: 0 | V95: 0 | W95: 0 | X95: 0 | Y95: 0 | Z95: 0 | AA95: 0 | AB95: 0 | AC95: 0 | AD95: 0 | AE95: 0 | AF95: =AF16 -> 28.564381 | AG95: =AF95 -> 28.564381 | AH95: =AG95 -> 28.564381 | AI95: =AH95 -> 28.564381 | AJ95: =AI95 -> 28.564381 | AK95: =AJ95 -> 28.564381 | AL95: =AK95 -> 28.564381
A96: Cohort M31 | B96: # | C96: 0 | D96: 0 | E96: 0 | F96: 0 | G96: 0 | H96: 0 | I96: 0 | J96: 0 | K96: 0 | L96: 0 | M96: 0 | N96: 0 | O96: 0 | P96: 0 | Q96: 0 | R96: 0 | S96: 0 | T96: 0 | U96: 0 | V96: 0 | W96: 0 | X96: 0 | Y96: 0 | Z96: 0 | AA96: 0 | AB96: 0 | AC96: 0 | AD96: 0 | AE96: 0 | AF96: 0 | AG96: =AG16 -> 29.44415 | AH96: =AG96 -> 29.44415 | AI96: =AH96 -> 29.44415 | AJ96: =AI96 -> 29.44415 | AK96: =AJ96 -> 29.44415 | AL96: =AK96 -> 29.44415
A97: Cohort M32 | B97: # | C97: 0 | D97: 0 | E97: 0 | F97: 0 | G97: 0 | H97: 0 | I97: 0 | J97: 0 | K97: 0 | L97: 0 | M97: 0 | N97: 0 | O97: 0 | P97: 0 | Q97: 0 | R97: 0 | S97: 0 | T97: 0 | U97: 0 | V97: 0 | W97: 0 | X97: 0 | Y97: 0 | Z97: 0 | AA97: 0 | AB97: 0 | AC97: 0 | AD97: 0 | AE97: 0 | AF97: 0 | AG97: 0 | AH97: =AH16 -> 30.389549 | AI97: =AH97 -> 30.389549 | AJ97: =AI97 -> 30.389549 | AK97: =AJ97 -> 30.389549 | AL97: =AK97 -> 30.389549
A98: Cohort M33 | B98: # | C98: 0 | D98: 0 | E98: 0 | F98: 0 | G98: 0 | H98: 0 | I98: 0 | J98: 0 | K98: 0 | L98: 0 | M98: 0 | N98: 0 | O98: 0 | P98: 0 | Q98: 0 | R98: 0 | S98: 0 | T98: 0 | U98: 0 | V98: 0 | W98: 0 | X98: 0 | Y98: 0 | Z98: 0 | AA98: 0 | AB98: 0 | AC98: 0 | AD98: 0 | AE98: 0 | AF98: 0 | AG98: 0 | AH98: 0 | AI98: =AI16 -> 31.406032 | AJ98: =AI98 -> 31.406032 | AK98: =AJ98 -> 31.406032 | AL98: =AK98 -> 31.406032
A99: Cohort M34 | B99: # | C99: 0 | D99: 0 | E99: 0 | F99: 0 | G99: 0 | H99: 0 | I99: 0 | J99: 0 | K99: 0 | L99: 0 | M99: 0 | N99: 0 | O99: 0 | P99: 0 | Q99: 0 | R99: 0 | S99: 0 | T99: 0 | U99: 0 | V99: 0 | W99: 0 | X99: 0 | Y99: 0 | Z99: 0 | AA99: 0 | AB99: 0 | AC99: 0 | AD99: 0 | AE99: 0 | AF99: 0 | AG99: 0 | AH99: 0 | AI99: 0 | AJ99: =AJ16 -> 31.755821 | AK99: =AJ99 -> 31.755821 | AL99: =AK99 -> 31.755821
A100: Cohort M35 | B100: # | C100: 0 | D100: 0 | E100: 0 | F100: 0 | G100: 0 | H100: 0 | I100: 0 | J100: 0 | K100: 0 | L100: 0 | M100: 0 | N100: 0 | O100: 0 | P100: 0 | Q100: 0 | R100: 0 | S100: 0 | T100: 0 | U100: 0 | V100: 0 | W100: 0 | X100: 0 | Y100: 0 | Z100: 0 | AA100: 0 | AB100: 0 | AC100: 0 | AD100: 0 | AE100: 0 | AF100: 0 | AG100: 0 | AH100: 0 | AI100: 0 | AJ100: 0 | AK100: =AK16 -> 31.814614 | AL100: =AK100 -> 31.814614
A101: Cohort M36 | B101: # | C101: 0 | D101: 0 | E101: 0 | F101: 0 | G101: 0 | H101: 0 | I101: 0 | J101: 0 | K101: 0 | L101: 0 | M101: 0 | N101: 0 | O101: 0 | P101: 0 | Q101: 0 | R101: 0 | S101: 0 | T101: 0 | U101: 0 | V101: 0 | W101: 0 | X101: 0 | Y101: 0 | Z101: 0 | AA101: 0 | AB101: 0 | AC101: 0 | AD101: 0 | AE101: 0 | AF101: 0 | AG101: 0 | AH101: 0 | AI101: 0 | AJ101: 0 | AK101: 0 | AL101: =AL16 -> 31.870723

Sheet P&L
A2: PROFIT & LOSS
A3: Billings are cash charged. Revenue is recognised. They differ by the annual prepayment — the gap is tracked on Cash Flow.
A5: Month index | B5: # | C5: 1 | D5: 2 | E5: 3 | F5: 4 | G5: 5 | H5: 6 | I5: 7 | J5: 8 | K5: 9 | L5: 10 | M5: 11 | N5: 12 | O5: 13 | P5: 14 | Q5: 15 | R5: 16 | S5: 17 | T5: 18 | U5: 19 | V5: 20 | W5: 21 | X5: 22 | Y5: 23 | Z5: 24 | AA5: 25 | AB5: 26 | AC5: 27 | AD5: 28 | AE5: 29 | AF5: 30 | AG5: 31 | AH5: 32 | AI5: 33 | AJ5: 34 | AK5: 35 | AL5: 36
A7: BILLINGS (cash charged to the customer)
A8: Monthly-plan customers billed | B8: # | C8: =Cohorts!C19 -> 7.92 | D8: =Cohorts!D19 -> 16.165336 | E8: =Cohorts!E19 -> 24.796723 | F8: =Cohorts!F19 -> 33.879782 | G8: =Cohorts!G19 -> 43.485674 | H8: =Cohorts!H19 -> 53.6918 | I8: =Cohorts!I19 -> 64.582577 | J8: =Cohorts!J19 -> 76.250296 | ... AL8: =Cohorts!AL19 -> 1246.6676
A9: Annual plans billed | B9: # | C9: =Cohorts!C23 -> 1.98 | D9: =Cohorts!D23 -> 2.180134 | E9: =Cohorts!E23 -> 2.4003268 | F9: =Cohorts!F23 -> 2.6427156 | G9: =Cohorts!G23 -> 2.9096696 | H9: =Cohorts!H23 -> 3.2038166 | I9: =Cohorts!I23 -> 3.5280713 | J9: =Cohorts!J23 -> 3.8856684 | ... AL9: =Cohorts!AL23 -> 47.822174
A10: Monthly-plan billings | B10: € | C10: =C8*Assumptions!$F$46 -> 95.04 | D10: =D8*Assumptions!$F$46 -> 193.98403 | E10: =E8*Assumptions!$F$46 -> 297.56068 | F10: =F8*Assumptions!$F$46 -> 406.55738 | G10: =G8*Assumptions!$F$46 -> 521.82808 | H10: =H8*Assumptions!$F$46 -> 644.3016 | I10: =I8*Assumptions!$F$46 -> 774.99092 | J10: =J8*Assumptions!$F$46 -> 915.00355 | ... AL10: =AL8*Assumptions!$F$46 -> 14960.011
A11: Annual-plan billings | B11: € | C11: =C9*Assumptions!$F$49 -> 237.6 | D11: =D9*Assumptions!$F$49 -> 261.61608 | E11: =E9*Assumptions!$F$49 -> 288.03922 | F11: =F9*Assumptions!$F$49 -> 317.12587 | G11: =G9*Assumptions!$F$49 -> 349.16036 | H11: =H9*Assumptions!$F$49 -> 384.45799 | I11: =I9*Assumptions!$F$49 -> 423.36856 | J11: =J9*Assumptions!$F$49 -> 466.2802 | ... AL11: =AL9*Assumptions!$F$49 -> 5738.6609
A12: Total billings | B12: € | C12: =C10+C11 -> 332.64 | D12: =D10+D11 -> 455.60011 | E12: =E10+E11 -> 585.59989 | F12: =F10+F11 -> 723.68325 | G12: =G10+G11 -> 870.98844 | H12: =H10+H11 -> 1028.7596 | I12: =I10+I11 -> 1198.3595 | J12: =J10+J11 -> 1381.2838 | ... AL12: =AL10+AL11 -> 20698.672
A13: Card transactions | B13: # | C13: =C8+C9 -> 9.9 | D13: =D8+D9 -> 18.34547 | E13: =E8+E9 -> 27.19705 | F13: =F8+F9 -> 36.522498 | G13: =G8+G9 -> 46.395343 | H13: =H8+H9 -> 56.895616 | I13: =I8+I9 -> 68.110648 | J13: =J8+J9 -> 80.135964 | ... AL13: =AL8+AL9 -> 1294.4898
A15: REVENUE (recognised)
A16: Monthly-plan subscription revenue | B16: € | C16: =Cohorts!C19*Assumptions!$F$46 -> 95.04 | D16: =Cohorts!D19*Assumptions!$F$46 -> 193.98403 | E16: =Cohorts!E19*Assumptions!$F$46 -> 297.56068 | F16: =Cohorts!F19*Assumptions!$F$46 -> 406.55738 | G16: =Cohorts!G19*Assumptions!$F$46 -> 521.82808 | H16: =Cohorts!H19*Assumptions!$F$46 -> 644.3016 | I16: =Cohorts!I19*Assumptions!$F$46 -> 774.99092 | J16: =Cohorts!J19*Assumptions!$F$46 -> 915.00355 | ... AL16: =Cohorts!AL19*Assumptions!$F$46 -> 14960.011
A17: Annual-plan subscription revenue | B17: € | C17: =Cohorts!C20*Assumptions!$F$47 -> 19.8 | D17: =Cohorts!D20*Assumptions!$F$47 -> 41.60134 | E17: =Cohorts!E20*Assumptions!$F$47 -> 65.604608 | F17: =Cohorts!F20*Assumptions!$F$47 -> 92.031764 | G17: =Cohorts!G20*Assumptions!$F$47 -> 121.12846 | H17: =Cohorts!H20*Assumptions!$F$47 -> 153.16663 | I17: =Cohorts!I20*Assumptions!$F$47 -> 188.44734 | J17: =Cohorts!J20*Assumptions!$F$47 -> 227.30402 | ... AL17: =Cohorts!AL20*Assumptions!$F$47 -> 4567.1958
A18: Total revenue (= MRR) | B18: € | C18: =C16+C17 -> 114.84 | D18: =D16+D17 -> 235.58537 | E18: =E16+E17 -> 363.16529 | F18: =F16+F17 -> 498.58915 | G18: =G16+G17 -> 642.95654 | H18: =H16+H17 -> 797.46822 | I18: =I16+I17 -> 963.43826 | J18: =J16+J17 -> 1142.3076 | ... AL18: =AL16+AL17 -> 19527.207
A19: ARR (run-rate) | B19: € | C19: =C18*12 -> 1378.08 | D19: =D18*12 -> 2827.0245 | E19: =E18*12 -> 4357.9834 | F19: =F18*12 -> 5983.0698 | G19: =G18*12 -> 7715.4785 | H19: =H18*12 -> 9569.6187 | I19: =I18*12 -> 11561.259 | J19: =J18*12 -> 13707.691 | ... AL19: =AL18*12 -> 234326.48
A20: Revenue growth MoM | B20: % | C20: =0 -> 0 | D20: =IF(C18=0,0,D18/C18-1) -> 1.0514226 | E20: =IF(D18=0,0,E18/D18-1) -> 0.54154429 | F20: =IF(E18=0,0,F18/E18-1) -> 0.3728987 | G20: =IF(F18=0,0,G18/F18-1) -> 0.28955182 | H20: =IF(G18=0,0,H18/G18-1) -> 0.24031434 | I20: =IF(H18=0,0,I18/H18-1) -> 0.2081212 | J20: =IF(I18=0,0,J18/I18-1) -> 0.18565726 | K20: =IF(J18=0,0,K18/J18-1) -> 0.16926376 | ... AL20: =IF(AK18=0,0,AL18/AK18-1) -> 0.049606269
A22: COST OF REVENUE
A23: Infrastructure & automation | B23: € | C23: =Cohorts!C21*Assumptions!$F$30 -> 3.465 | D23: =Cohorts!D21*Assumptions!$F$30 -> 7.1139145 | E23: =Cohorts!E21*Assumptions!$F$30 -> 10.975014 | F23: =Cohorts!F21*Assumptions!$F$30 -> 15.079035 | G23: =Cohorts!G21*Assumptions!$F$30 -> 19.459482 | H23: =Cohorts!H21*Assumptions!$F$30 -> 24.152962 | I23: =Cohorts!I21*Assumptions!$F$30 -> 29.199559 | J23: =Cohorts!J21*Assumptions!$F$30 -> 34.643244 | ... AL23: =Cohorts!AL21*Assumptions!$F$30 -> 596.18551
A24: Email & messaging | B24: € | C24: =Cohorts!C21*Assumptions!$F$31 -> 0.99 | D24: =Cohorts!D21*Assumptions!$F$31 -> 2.032547 | E24: =Cohorts!E21*Assumptions!$F$31 -> 3.1357184 | F24: =Cohorts!F21*Assumptions!$F$31 -> 4.3082958 | G24: =Cohorts!G21*Assumptions!$F$31 -> 5.559852 | H24: =Cohorts!H21*Assumptions!$F$31 -> 6.9008462 | I24: =Cohorts!I21*Assumptions!$F$31 -> 8.3427311 | J24: =Cohorts!J21*Assumptions!$F$31 -> 9.8980698 | ... AL24: =Cohorts!AL21*Assumptions!$F$31 -> 170.33872
A25: Customer support | B25: € | C25: =Cohorts!C21*Assumptions!$F$32 -> 2.97 | D25: =Cohorts!D21*Assumptions!$F$32 -> 6.097641 | E25: =Cohorts!E21*Assumptions!$F$32 -> 9.4071552 | F25: =Cohorts!F21*Assumptions!$F$32 -> 12.924888 | G25: =Cohorts!G21*Assumptions!$F$32 -> 16.679556 | H25: =Cohorts!H21*Assumptions!$F$32 -> 20.702539 | I25: =Cohorts!I21*Assumptions!$F$32 -> 25.028193 | J25: =Cohorts!J21*Assumptions!$F$32 -> 29.694209 | ... AL25: =Cohorts!AL21*Assumptions!$F$32 -> 511.01615
A26: Payment processing | B26: € | C26: =C12*Assumptions!$F$33+C13*Assumptions!$F$34 -> 7.4646 | D26: =D12*Assumptions!$F$33+D13*Assumptions!$F$34 -> 11.420369 | E26: =E12*Assumptions!$F$33+E13*Assumptions!$F$34 -> 15.583261 | F26: =F12*Assumptions!$F$33+F13*Assumptions!$F$34 -> 19.985873 | G26: =G12*Assumptions!$F$33+G13*Assumptions!$F$34 -> 24.663662 | H26: =H12*Assumptions!$F$33+H13*Assumptions!$F$34 -> 29.655298 | I26: =I12*Assumptions!$F$33+I13*Assumptions!$F$34 -> 35.003054 | J26: =J12*Assumptions!$F$33+J13*Assumptions!$F$34 -> 40.753247 | ... AL26: =AL12*Assumptions!$F$33+AL13*Assumptions!$F$34 -> 634.10252
A27: Fixed platform cost | B27: € | C27: =Assumptions!$F$35 -> 70 | D27: =Assumptions!$F$35 -> 70 | E27: =Assumptions!$F$35 -> 70 | F27: =Assumptions!$F$35 -> 70 | G27: =Assumptions!$F$35 -> 70 | H27: =Assumptions!$F$35 -> 70 | I27: =Assumptions!$F$35 -> 70 | J27: =Assumptions!$F$35 -> 70 | ... AL27: =Assumptions!$F$35 -> 70
A28: Total cost of revenue | B28: € | C28: =SUM(C23:C27) -> 84.8896 | D28: =SUM(D23:D27) -> 96.664472 | E28: =SUM(E23:E27) -> 109.10115 | F28: =SUM(F23:F27) -> 122.29809 | G28: =SUM(G23:G27) -> 136.36255 | H28: =SUM(H23:H27) -> 151.41164 | I28: =SUM(I23:I27) -> 167.57354 | J28: =SUM(J23:J27) -> 184.98877 | ... AL28: =SUM(AL23:AL27) -> 1981.6429
A30: Gross profit | B30: € | C30: =C18-C28 -> 29.9504 | D30: =D18-D28 -> 138.9209 | E30: =E18-E28 -> 254.06414 | F30: =F18-F28 -> 376.29106 | G30: =G18-G28 -> 506.59399 | H30: =H18-H28 -> 646.05658 | I30: =I18-I28 -> 795.86472 | J30: =J18-J28 -> 957.3188 | ... AL30: =AL18-AL28 -> 17545.564
A31: Gross margin | B31: % | C31: =IF(C18=0,0,C30/C18) -> 0.26080111 | D31: =IF(D18=0,0,D30/D18) -> 0.5896839 | E31: =IF(E18=0,0,E30/E18) -> 0.69958266 | F31: =IF(F18=0,0,F30/F18) -> 0.75471169 | G31: =IF(G18=0,0,G30/G18) -> 0.78791327 | H31: =IF(H18=0,0,H30/H18) -> 0.81013457 | I31: =IF(I18=0,0,I30/I18) -> 0.82606718 | J31: =IF(J18=0,0,J30/J18) -> 0.83805695 | ... AL31: =IF(AL18=0,0,AL30/AL18) -> 0.89851888
A33: OPERATING EXPENSES
A34: Paid marketing | B34: € | C34: =Cohorts!C8 -> 500 | D34: =Cohorts!D8 -> 540 | E34: =Cohorts!E8 -> 583.2 | F34: =Cohorts!F8 -> 629.856 | G34: =Cohorts!G8 -> 680.24448 | H34: =Cohorts!H8 -> 734.66404 | I34: =Cohorts!I8 -> 793.43716 | J34: =Cohorts!J8 -> 856.91213 | ... AL34: =Cohorts!AL8 -> 6000
A35: Founder compensation | B35: € | C35: =IF(C5>=Assumptions!$F$38,Assumptions!$F$37,0) -> 0 | D35: =IF(D5>=Assumptions!$F$38,Assumptions!$F$37,0) -> 0 | E35: =IF(E5>=Assumptions!$F$38,Assumptions!$F$37,0) -> 0 | F35: =IF(F5>=Assumptions!$F$38,Assumptions!$F$37,0) -> 0 | G35: =IF(G5>=Assumptions!$F$38,Assumptions!$F$37,0) -> 0 | H35: =IF(H5>=Assumptions!$F$38,Assumptions!$F$37,0) -> 0 | I35: =IF(I5>=Assumptions!$F$38,Assumptions!$F$37,0) -> 0 | J35: =IF(J5>=Assumptions!$F$38,Assumptions!$F$37,0) -> 0 | ... AL35: =IF(AL5>=Assumptions!$F$38,Assumptions!$F$37,0) -> 2500
A36: Tools & software | B36: € | C36: =Assumptions!$F$39*(1+Assumptions!$F$41)^(C5-1) -> 120 | D36: =Assumptions!$F$39*(1+Assumptions!$F$41)^(D5-1) -> 120.6 | E36: =Assumptions!$F$39*(1+Assumptions!$F$41)^(E5-1) -> 121.203 | F36: =Assumptions!$F$39*(1+Assumptions!$F$41)^(F5-1) -> 121.80902 | G36: =Assumptions!$F$39*(1+Assumptions!$F$41)^(G5-1) -> 122.41806 | H36: =Assumptions!$F$39*(1+Assumptions!$F$41)^(H5-1) -> 123.03015 | I36: =Assumptions!$F$39*(1+Assumptions!$F$41)^(I5-1) -> 123.6453 | J36: =Assumptions!$F$39*(1+Assumptions!$F$41)^(J5-1) -> 124.26353 | ... AL36: =Assumptions!$F$39*(1+Assumptions!$F$41)^(AL5-1) -> 142.88723
A37: Legal, accounting & admin | B37: € | C37: =Assumptions!$F$40*(1+Assumptions!$F$41)^(C5-1) -> 80 | D37: =Assumptions!$F$40*(1+Assumptions!$F$41)^(D5-1) -> 80.4 | E37: =Assumptions!$F$40*(1+Assumptions!$F$41)^(E5-1) -> 80.802 | F37: =Assumptions!$F$40*(1+Assumptions!$F$41)^(F5-1) -> 81.20601 | G37: =Assumptions!$F$40*(1+Assumptions!$F$41)^(G5-1) -> 81.61204 | H37: =Assumptions!$F$40*(1+Assumptions!$F$41)^(H5-1) -> 82.0201 | I37: =Assumptions!$F$40*(1+Assumptions!$F$41)^(I5-1) -> 82.430201 | J37: =Assumptions!$F$40*(1+Assumptions!$F$41)^(J5-1) -> 82.842352 | ... AL37: =Assumptions!$F$40*(1+Assumptions!$F$41)^(AL5-1) -> 95.258151
A38: Total operating expenses | B38: € | C38: =SUM(C34:C37) -> 700 | D38: =SUM(D34:D37) -> 741 | E38: =SUM(E34:E37) -> 785.205 | F38: =SUM(F34:F37) -> 832.87103 | G38: =SUM(G34:G37) -> 884.27458 | H38: =SUM(H34:H37) -> 939.71429 | I38: =SUM(I34:I37) -> 999.51266 | J38: =SUM(J34:J37) -> 1064.018 | ... AL38: =SUM(AL34:AL37) -> 8738.1454
A40: EBITDA | B40: € | C40: =C30-C38 -> -670.0496 | D40: =D30-D38 -> -602.0791 | E40: =E30-E38 -> -531.14086 | F40: =F30-F38 -> -456.57997 | G40: =G30-G38 -> -377.68059 | H40: =H30-H38 -> -293.65771 | I40: =I30-I38 -> -203.64794 | J40: =J30-J38 -> -106.69921 | ... AL40: =AL30-AL38 -> 8807.4186
A41: EBITDA margin | B41: % | C41: =IF(C18=0,0,C40/C18) -> -5.834636 | D41: =IF(D18=0,0,D40/D18) -> -2.5556727 | E41: =IF(E18=0,0,E40/E18) -> -1.462532 | F41: =IF(F18=0,0,F40/F18) -> -0.9157439 | G41: =IF(G18=0,0,G40/G18) -> -0.58741231 | H41: =IF(H18=0,0,H40/H18) -> -0.36823751 | I41: =IF(I18=0,0,I40/I18) -> -0.21137622 | J41: =IF(J18=0,0,J40/J18) -> -0.093406729 | ... AL41: =IF(AL18=0,0,AL40/AL18) -> 0.4510332
A42: Cumulative EBITDA | B42: € | C42: =C40 -> -670.0496 | D42: =C42+D40 -> -1272.1287 | E42: =D42+E40 -> -1803.2696 | F42: =E42+F40 -> -2259.8495 | G42: =F42+G40 -> -2637.5301 | H42: =G42+H40 -> -2931.1878 | I42: =H42+I40 -> -3134.8358 | J42: =I42+J40 -> -3241.535 | K42: =J42+K40 -> -3243.2944 | ... AL42: =AK42+AL40 -> 49272.658
A43: MEMO
A44: Month flag — EBITDA positive | B44: # | C44: =IF(C40>0,C5,9999) -> 9999 | D44: =IF(D40>0,D5,9999) -> 9999 | E44: =IF(E40>0,E5,9999) -> 9999 | F44: =IF(F40>0,F5,9999) -> 9999 | G44: =IF(G40>0,G5,9999) -> 9999 | H44: =IF(H40>0,H5,9999) -> 9999 | I44: =IF(I40>0,I5,9999) -> 9999 | J44: =IF(J40>0,J5,9999) -> 9999 | ... AL44: =IF(AL40>0,AL5,9999) -> 36
A45: 9999 = not yet positive. Dashboard takes the MIN of this row.

Sheet Cash Flow
A2: CASH FLOW & DEFERRED REVENUE
A3: Card payments are collected on charge, so collections equal billings. The gap between cash and EBITDA is the annual prepayment, and it is checked every month.
A5: Month index | B5: # | C5: 1 | D5: 2 | E5: 3 | F5: 4 | G5: 5 | H5: 6 | I5: 7 | J5: 8 | K5: 9 | L5: 10 | M5: 11 | N5: 12 | O5: 13 | P5: 14 | Q5: 15 | R5: 16 | S5: 17 | T5: 18 | U5: 19 | V5: 20 | W5: 21 | X5: 22 | Y5: 23 | Z5: 24 | AA5: 25 | AB5: 26 | AC5: 27 | AD5: 28 | AE5: 29 | AF5: 30 | AG5: 31 | AH5: 32 | AI5: 33 | AJ5: 34 | AK5: 35 | AL5: 36
A7: CASH WALK
A8: Opening cash | B8: € | C8: =Assumptions!$F$43 -> 5000 | D8: =C13 -> 4547.7504 | E8: =D13 -> 4165.686 | F8: =E13 -> 3856.9798 | G8: =F13 -> 3625.4939 | H8: =G13 -> 3475.8452 | I8: =H13 -> 3413.4789 | J8: =I13 -> 3444.7522 | K8: =J13 -> 3577.0291 | ... AL8: =AK13 -> 72149.53
A9: Collections (= total billings) | B9: € | C9: ='P&L'!C12 -> 332.64 | D9: ='P&L'!D12 -> 455.60011 | E9: ='P&L'!E12 -> 585.59989 | F9: ='P&L'!F12 -> 723.68325 | G9: ='P&L'!G12 -> 870.98844 | H9: ='P&L'!H12 -> 1028.7596 | I9: ='P&L'!I12 -> 1198.3595 | J9: ='P&L'!J12 -> 1381.2838 | ... AL9: ='P&L'!AL12 -> 20698.672
A10: Cost of revenue paid | B10: € | C10: =-'P&L'!C28 -> -84.8896 | D10: =-'P&L'!D28 -> -96.664472 | E10: =-'P&L'!E28 -> -109.10115 | F10: =-'P&L'!F28 -> -122.29809 | G10: =-'P&L'!G28 -> -136.36255 | H10: =-'P&L'!H28 -> -151.41164 | I10: =-'P&L'!I28 -> -167.57354 | J10: =-'P&L'!J28 -> -184.98877 | ... AL10: =-'P&L'!AL28 -> -1981.6429
A11: Operating expenses paid | B11: € | C11: =-'P&L'!C38 -> -700 | D11: =-'P&L'!D38 -> -741 | E11: =-'P&L'!E38 -> -785.205 | F11: =-'P&L'!F38 -> -832.87103 | G11: =-'P&L'!G38 -> -884.27458 | H11: =-'P&L'!H38 -> -939.71429 | I11: =-'P&L'!I38 -> -999.51266 | J11: =-'P&L'!J38 -> -1064.018 | ... AL11: =-'P&L'!AL38 -> -8738.1454
A12: Net cash flow | B12: € | C12: =SUM(C9:C11) -> -452.2496 | D12: =SUM(D9:D11) -> -382.06436 | E12: =SUM(E9:E11) -> -308.70625 | F12: =SUM(F9:F11) -> -231.48586 | G12: =SUM(G9:G11) -> -149.64869 | H12: =SUM(H9:H11) -> -62.366348 | I12: =SUM(I9:I11) -> 31.273278 | J12: =SUM(J9:J11) -> 132.27697 | ... AL12: =SUM(AL9:AL11) -> 9978.8836
A13: Closing cash | B13: € | C13: =C8+C12 -> 4547.7504 | D13: =D8+D12 -> 4165.686 | E13: =E8+E12 -> 3856.9798 | F13: =F8+F12 -> 3625.4939 | G13: =G8+G12 -> 3475.8452 | H13: =H8+H12 -> 3413.4789 | I13: =I8+I12 -> 3444.7522 | J13: =J8+J12 -> 3577.0291 | ... AL13: =AL8+AL12 -> 82128.413
A15: DEFERRED REVENUE ROLLFORWARD (annual prepayments)
A16: Opening deferred revenue | B16: € | C16: =0 -> 0 | D16: =C19 -> 217.8 | E16: =D19 -> 437.81474 | F16: =E19 -> 660.24935 | G16: =F19 -> 885.34345 | H16: =G19 -> 1113.3754 | I16: =H19 -> 1344.6667 | J16: =I19 -> 1579.5879 | K16: =J19 -> 1818.5641 | ... AL16: =AK19 -> 26684.29
A17: Annual billings received | B17: € | C17: ='P&L'!C11 -> 237.6 | D17: ='P&L'!D11 -> 261.61608 | E17: ='P&L'!E11 -> 288.03922 | F17: ='P&L'!F11 -> 317.12587 | G17: ='P&L'!G11 -> 349.16036 | H17: ='P&L'!H11 -> 384.45799 | I17: ='P&L'!I11 -> 423.36856 | J17: ='P&L'!J11 -> 466.2802 | ... AL17: ='P&L'!AL11 -> 5738.6609
A18: Recognised into revenue | B18: € | C18: =-'P&L'!C17 -> -19.8 | D18: =-'P&L'!D17 -> -41.60134 | E18: =-'P&L'!E17 -> -65.604608 | F18: =-'P&L'!F17 -> -92.031764 | G18: =-'P&L'!G17 -> -121.12846 | H18: =-'P&L'!H17 -> -153.16663 | I18: =-'P&L'!I17 -> -188.44734 | J18: =-'P&L'!J17 -> -227.30402 | ... AL18: =-'P&L'!AL17 -> -4567.1958
A19: Closing deferred revenue | B19: € | C19: =SUM(C16:C18) -> 217.8 | D19: =SUM(D16:D18) -> 437.81474 | E19: =SUM(E16:E18) -> 660.24935 | F19: =SUM(F16:F18) -> 885.34345 | G19: =SUM(G16:G18) -> 1113.3754 | H19: =SUM(H16:H18) -> 1344.6667 | I19: =SUM(I16:I18) -> 1579.5879 | J19: =SUM(J16:J18) -> 1818.5641 | ... AL19: =SUM(AL16:AL18) -> 27855.755
A21: INTEGRITY CHECK
A22: EBITDA | B22: € | C22: ='P&L'!C40 -> -670.0496 | D22: ='P&L'!D40 -> -602.0791 | E22: ='P&L'!E40 -> -531.14086 | F22: ='P&L'!F40 -> -456.57997 | G22: ='P&L'!G40 -> -377.68059 | H22: ='P&L'!H40 -> -293.65771 | I22: ='P&L'!I40 -> -203.64794 | J22: ='P&L'!J40 -> -106.69921 | ... AL22: ='P&L'!AL40 -> 8807.4186
A23: Δ deferred revenue | B23: € | C23: =C19-C16 -> 217.8 | D23: =D19-D16 -> 220.01474 | E23: =E19-E16 -> 222.43461 | F23: =F19-F16 -> 225.09411 | G23: =G19-G16 -> 228.0319 | H23: =H19-H16 -> 231.29136 | I23: =I19-I16 -> 234.92122 | J23: =J19-J16 -> 238.97618 | ... AL23: =AL19-AL16 -> 1171.4651
A24: Check: net cash − EBITDA − Δdeferred | B24: € | C24: =ROUND(C12-C22-C23,6) -> 0 | D24: =ROUND(D12-D22-D23,6) -> 0 | E24: =ROUND(E12-E22-E23,6) -> 0 | F24: =ROUND(F12-F22-F23,6) -> 0 | G24: =ROUND(G12-G22-G23,6) -> 0 | H24: =ROUND(H12-H22-H23,6) -> 0 | I24: =ROUND(I12-I22-I23,6) -> 0 | J24: =ROUND(J12-J22-J23,6) -> 0 | ... AL24: =ROUND(AL12-AL22-AL23,6) -> 0
A25: Must be zero in every month. Any non-zero cell means the P&L and the cash walk have come apart — stop and fix before reading anything else.
A26: MEMO
A27: Month flag — net cash flow positive | B27: # | C27: =IF(C12>0,C5,9999) -> 9999 | D27: =IF(D12>0,D5,9999) -> 9999 | E27: =IF(E12>0,E5,9999) -> 9999 | F27: =IF(F12>0,F5,9999) -> 9999 | G27: =IF(G12>0,G5,9999) -> 9999 | H27: =IF(H12>0,H5,9999) -> 9999 | I27: =IF(I12>0,I5,9999) -> 7 | J27: =IF(J12>0,J5,9999) -> 8 | ... AL27: =IF(AL12>0,AL5,9999) -> 36

Sheet Unit Economics
A2: UNIT ECONOMICS
A3: Steady-state economics on the live scenario, then two grids showing how fast the verdict changes.
A5: VALUE OF A CUSTOMER
A6: Blended ARPU | B6: € / month | C6: =Assumptions!$F$48 -> 11.6 | L6: Across monthly and annual plans.
A7: Gross margin (month 36, at scale) | B7: % | C7: ='P&L'!AL31 -> 0.89851888 | L7: Taken at month 36 so fixed platform cost is spread over the mature base — not the month-1 margin.
A8: Gross profit per customer / month | B8: € | C8: =C6*C7 -> 10.422819
A9: Blended monthly churn | B9: % | C9: =Assumptions!$F$51 -> 0.053857106
A10: Average customer lifetime | B10: months | C10: =Assumptions!$F$52 -> 18.567652 | L10: 1 / blended churn.
A11: LTV | B11: € | C11: =C8*C10 -> 193.52727 | L11: Gross-profit LTV, undiscounted.
A13: COST OF A CUSTOMER
A14: Paid CAC (funnel maths) | B14: € | C14: =Assumptions!$F$53 -> 90.909091 | L14: CPC / (signup rate x trial-to-paid). What the marginal paid customer costs.
A15: Total paid marketing, 36 months | B15: € | C15: =SUM('P&L'!C34:AL34) -> 90975.31
A16: Total new customers, 36 months | B16: # | C16: =SUM(Cohorts!C14:AL14) -> 2599.5125
A17: Blended CAC | B17: € | C17: =IF(C16=0,0,C15/C16) -> 34.997065 | L17: All marketing spend over all new customers, including the organic and referral ones that cost nothing. Flattering — quote paid CAC to anyone serious.
A19: VERDICT
A20: LTV : CAC — paid | B20: x | C20: =IF(C14=0,0,C11/C14) -> 2.1288 | L20: The honest one. Below 3.0x, paid acquisition does not fund itself.
A21: LTV : CAC — blended | B21: x | C21: =IF(C17=0,0,C11/C17) -> 5.5298144 | L21: Includes free channels.
A22: CAC payback — paid | B22: months | C22: =IF(C8=0,0,C14/C8) -> 8.7221213 | L22: Months of gross profit to repay one paid customer. Must be comfortably below average lifetime (row 10) or the customer leaves before repaying.
A23: CAC payback — blended | B23: months | C23: =IF(C8=0,0,C17/C8) -> 3.3577351
A24: Profitable months after payback | B24: months | C24: =C10-C22 -> 9.8455307 | L24: Average lifetime minus payback. This is the only window in which a customer actually makes money. Negative means the average customer leaves still owing you their acquisition cost.
A27: SENSITIVITY — LTV : CAC (paid)
A28: Blended monthly churn ↓ / Trial-to-paid → | L28: Grid recomputes from the live ARPU, gross margin, CPC and signup rate. Green ≥ 3.0x, amber 2.0–3.0x, red < 2.0x — the standard venture bar.
D29: 0.12 | E29: 0.15 | F29: 0.18 | G29: 0.22 | H29: 0.25 | I29: 0.28 | J29: 0.32
C30: 0.04 | D30: =IF(OR($C30=0,D$29=0,Assumptions!$F$19=0),0,(($C$6*$C$7)/$C30)/(Assumptions!$F$19/(Assumptions!$F$20*D$29))) -> 1.5634228 | E30: =IF(OR($C30=0,E$29=0,Assumptions!$F$19=0),0,(($C$6*$C$7)/$C30)/(Assumptions!$F$19/(Assumptions!$F$20*E$29))) -> 1.9542786 | F30: =IF(OR($C30=0,F$29=0,Assumptions!$F$19=0),0,(($C$6*$C$7)/$C30)/(Assumptions!$F$19/(Assumptions!$F$20*F$29))) -> 2.3451343 | G30: =IF(OR($C30=0,G$29=0,Assumptions!$F$19=0),0,(($C$6*$C$7)/$C30)/(Assumptions!$F$19/(Assumptions!$F$20*G$29))) -> 2.8662752 | H30: =IF(OR($C30=0,H$29=0,Assumptions!$F$19=0),0,(($C$6*$C$7)/$C30)/(Assumptions!$F$19/(Assumptions!$F$20*H$29))) -> 3.2571309 | I30: =IF(OR($C30=0,I$29=0,Assumptions!$F$19=0),0,(($C$6*$C$7)/$C30)/(Assumptions!$F$19/(Assumptions!$F$20*I$29))) -> 3.6479866 | J30: =IF(OR($C30=0,J$29=0,Assumptions!$F$19=0),0,(($C$6*$C$7)/$C30)/(Assumptions!$F$19/(Assumptions!$F$20*J$29))) -> 4.1691276
C31: 0.045 | D31: =IF(OR($C31=0,D$29=0,Assumptions!$F$19=0),0,(($C$6*$C$7)/$C31)/(Assumptions!$F$19/(Assumptions!$F$20*D$29))) -> 1.3897092 | E31: =IF(OR($C31=0,E$29=0,Assumptions!$F$19=0),0,(($C$6*$C$7)/$C31)/(Assumptions!$F$19/(Assumptions!$F$20*E$29))) -> 1.7371365 | F31: =IF(OR($C31=0,F$29=0,Assumptions!$F$19=0),0,(($C$6*$C$7)/$C31)/(Assumptions!$F$19/(Assumptions!$F$20*F$29))) -> 2.0845638 | G31: =IF(OR($C31=0,G$29=0,Assumptions!$F$19=0),0,(($C$6*$C$7)/$C31)/(Assumptions!$F$19/(Assumptions!$F$20*G$29))) -> 2.5478002 | H31: =IF(OR($C31=0,H$29=0,Assumptions!$F$19=0),0,(($C$6*$C$7)/$C31)/(Assumptions!$F$19/(Assumptions!$F$20*H$29))) -> 2.8952275 | I31: =IF(OR($C31=0,I$29=0,Assumptions!$F$19=0),0,(($C$6*$C$7)/$C31)/(Assumptions!$F$19/(Assumptions!$F$20*I$29))) -> 3.2426548 | J31: =IF(OR($C31=0,J$29=0,Assumptions!$F$19=0),0,(($C$6*$C$7)/$C31)/(Assumptions!$F$19/(Assumptions!$F$20*J$29))) -> 3.7058912
C32: 0.05 | D32: =IF(OR($C32=0,D$29=0,Assumptions!$F$19=0),0,(($C$6*$C$7)/$C32)/(Assumptions!$F$19/(Assumptions!$F$20*D$29))) -> 1.2507383 | E32: =IF(OR($C32=0,E$29=0,Assumptions!$F$19=0),0,(($C$6*$C$7)/$C32)/(Assumptions!$F$19/(Assumptions!$F$20*E$29))) -> 1.5634228 | F32: =IF(OR($C32=0,F$29=0,Assumptions!$F$19=0),0,(($C$6*$C$7)/$C32)/(Assumptions!$F$19/(Assumptions!$F$20*F$29))) -> 1.8761074 | G32: =IF(OR($C32=0,G$29=0,Assumptions!$F$19=0),0,(($C$6*$C$7)/$C32)/(Assumptions!$F$19/(Assumptions!$F$20*G$29))) -> 2.2930202 | H32: =IF(OR($C32=0,H$29=0,Assumptions!$F$19=0),0,(($C$6*$C$7)/$C32)/(Assumptions!$F$19/(Assumptions!$F$20*H$29))) -> 2.6057047 | I32: =IF(OR($C32=0,I$29=0,Assumptions!$F$19=0),0,(($C$6*$C$7)/$C32)/(Assumptions!$F$19/(Assumptions!$F$20*I$29))) -> 2.9183893 | J32: =IF(OR($C32=0,J$29=0,Assumptions!$F$19=0),0,(($C$6*$C$7)/$C32)/(Assumptions!$F$19/(Assumptions!$F$20*J$29))) -> 3.3353021
C33: 0.06 | D33: =IF(OR($C33=0,D$29=0,Assumptions!$F$19=0),0,(($C$6*$C$7)/$C33)/(Assumptions!$F$19/(Assumptions!$F$20*D$29))) -> 1.0422819 | E33: =IF(OR($C33=0,E$29=0,Assumptions!$F$19=0),0,(($C$6*$C$7)/$C33)/(Assumptions!$F$19/(Assumptions!$F$20*E$29))) -> 1.3028524 | F33: =IF(OR($C33=0,F$29=0,Assumptions!$F$19=0),0,(($C$6*$C$7)/$C33)/(Assumptions!$F$19/(Assumptions!$F$20*F$29))) -> 1.5634228 | G33: =IF(OR($C33=0,G$29=0,Assumptions!$F$19=0),0,(($C$6*$C$7)/$C33)/(Assumptions!$F$19/(Assumptions!$F$20*G$29))) -> 1.9108501 | H33: =IF(OR($C33=0,H$29=0,Assumptions!$F$19=0),0,(($C$6*$C$7)/$C33)/(Assumptions!$F$19/(Assumptions!$F$20*H$29))) -> 2.1714206 | I33: =IF(OR($C33=0,I$29=0,Assumptions!$F$19=0),0,(($C$6*$C$7)/$C33)/(Assumptions!$F$19/(Assumptions!$F$20*I$29))) -> 2.4319911 | J33: =IF(OR($C33=0,J$29=0,Assumptions!$F$19=0),0,(($C$6*$C$7)/$C33)/(Assumptions!$F$19/(Assumptions!$F$20*J$29))) -> 2.7794184
C34: 0.07 | D34: =IF(OR($C34=0,D$29=0,Assumptions!$F$19=0),0,(($C$6*$C$7)/$C34)/(Assumptions!$F$19/(Assumptions!$F$20*D$29))) -> 0.89338448 | E34: =IF(OR($C34=0,E$29=0,Assumptions!$F$19=0),0,(($C$6*$C$7)/$C34)/(Assumptions!$F$19/(Assumptions!$F$20*E$29))) -> 1.1167306 | F34: =IF(OR($C34=0,F$29=0,Assumptions!$F$19=0),0,(($C$6*$C$7)/$C34)/(Assumptions!$F$19/(Assumptions!$F$20*F$29))) -> 1.3400767 | G34: =IF(OR($C34=0,G$29=0,Assumptions!$F$19=0),0,(($C$6*$C$7)/$C34)/(Assumptions!$F$19/(Assumptions!$F$20*G$29))) -> 1.6378716 | H34: =IF(OR($C34=0,H$29=0,Assumptions!$F$19=0),0,(($C$6*$C$7)/$C34)/(Assumptions!$F$19/(Assumptions!$F$20*H$29))) -> 1.8612177 | I34: =IF(OR($C34=0,I$29=0,Assumptions!$F$19=0),0,(($C$6*$C$7)/$C34)/(Assumptions!$F$19/(Assumptions!$F$20*I$29))) -> 2.0845638 | J34: =IF(OR($C34=0,J$29=0,Assumptions!$F$19=0),0,(($C$6*$C$7)/$C34)/(Assumptions!$F$19/(Assumptions!$F$20*J$29))) -> 2.3823586
C35: 0.08 | D35: =IF(OR($C35=0,D$29=0,Assumptions!$F$19=0),0,(($C$6*$C$7)/$C35)/(Assumptions!$F$19/(Assumptions!$F$20*D$29))) -> 0.78171142 | E35: =IF(OR($C35=0,E$29=0,Assumptions!$F$19=0),0,(($C$6*$C$7)/$C35)/(Assumptions!$F$19/(Assumptions!$F$20*E$29))) -> 0.97713928 | F35: =IF(OR($C35=0,F$29=0,Assumptions!$F$19=0),0,(($C$6*$C$7)/$C35)/(Assumptions!$F$19/(Assumptions!$F$20*F$29))) -> 1.1725671 | G35: =IF(OR($C35=0,G$29=0,Assumptions!$F$19=0),0,(($C$6*$C$7)/$C35)/(Assumptions!$F$19/(Assumptions!$F$20*G$29))) -> 1.4331376 | H35: =IF(OR($C35=0,H$29=0,Assumptions!$F$19=0),0,(($C$6*$C$7)/$C35)/(Assumptions!$F$19/(Assumptions!$F$20*H$29))) -> 1.6285655 | I35: =IF(OR($C35=0,I$29=0,Assumptions!$F$19=0),0,(($C$6*$C$7)/$C35)/(Assumptions!$F$19/(Assumptions!$F$20*I$29))) -> 1.8239933 | J35: =IF(OR($C35=0,J$29=0,Assumptions!$F$19=0),0,(($C$6*$C$7)/$C35)/(Assumptions!$F$19/(Assumptions!$F$20*J$29))) -> 2.0845638
C36: 0.09 | D36: =IF(OR($C36=0,D$29=0,Assumptions!$F$19=0),0,(($C$6*$C$7)/$C36)/(Assumptions!$F$19/(Assumptions!$F$20*D$29))) -> 0.6948546 | E36: =IF(OR($C36=0,E$29=0,Assumptions!$F$19=0),0,(($C$6*$C$7)/$C36)/(Assumptions!$F$19/(Assumptions!$F$20*E$29))) -> 0.86856825 | F36: =IF(OR($C36=0,F$29=0,Assumptions!$F$19=0),0,(($C$6*$C$7)/$C36)/(Assumptions!$F$19/(Assumptions!$F$20*F$29))) -> 1.0422819 | G36: =IF(OR($C36=0,G$29=0,Assumptions!$F$19=0),0,(($C$6*$C$7)/$C36)/(Assumptions!$F$19/(Assumptions!$F$20*G$29))) -> 1.2739001 | H36: =IF(OR($C36=0,H$29=0,Assumptions!$F$19=0),0,(($C$6*$C$7)/$C36)/(Assumptions!$F$19/(Assumptions!$F$20*H$29))) -> 1.4476137 | I36: =IF(OR($C36=0,I$29=0,Assumptions!$F$19=0),0,(($C$6*$C$7)/$C36)/(Assumptions!$F$19/(Assumptions!$F$20*I$29))) -> 1.6213274 | J36: =IF(OR($C36=0,J$29=0,Assumptions!$F$19=0),0,(($C$6*$C$7)/$C36)/(Assumptions!$F$19/(Assumptions!$F$20*J$29))) -> 1.8529456
A39: SENSITIVITY — CAC payback (months, paid)
A40: Blended CPC ↓ / Trial-to-paid → | L40: Compare every cell against average customer lifetime on row 10. Any cell above it means the customer churns before paying you back.
D41: 0.12 | E41: 0.15 | F41: 0.18 | G41: 0.22 | H41: 0.25 | I41: 0.28 | J41: 0.32
C42: 0.4 | D42: =IF(OR(D$41=0,$C$6*$C$7=0),0,($C42/(Assumptions!$F$20*D$41))/($C$6*$C$7)) -> 7.9952778 | E42: =IF(OR(E$41=0,$C$6*$C$7=0),0,($C42/(Assumptions!$F$20*E$41))/($C$6*$C$7)) -> 6.3962223 | F42: =IF(OR(F$41=0,$C$6*$C$7=0),0,($C42/(Assumptions!$F$20*F$41))/($C$6*$C$7)) -> 5.3301852 | G42: =IF(OR(G$41=0,$C$6*$C$7=0),0,($C42/(Assumptions!$F$20*G$41))/($C$6*$C$7)) -> 4.3610606 | H42: =IF(OR(H$41=0,$C$6*$C$7=0),0,($C42/(Assumptions!$F$20*H$41))/($C$6*$C$7)) -> 3.8377334 | I42: =IF(OR(I$41=0,$C$6*$C$7=0),0,($C42/(Assumptions!$F$20*I$41))/($C$6*$C$7)) -> 3.4265476 | J42: =IF(OR(J$41=0,$C$6*$C$7=0),0,($C42/(Assumptions!$F$20*J$41))/($C$6*$C$7)) -> 2.9982292
C43: 0.6 | D43: =IF(OR(D$41=0,$C$6*$C$7=0),0,($C43/(Assumptions!$F$20*D$41))/($C$6*$C$7)) -> 11.992917 | E43: =IF(OR(E$41=0,$C$6*$C$7=0),0,($C43/(Assumptions!$F$20*E$41))/($C$6*$C$7)) -> 9.5943334 | F43: =IF(OR(F$41=0,$C$6*$C$7=0),0,($C43/(Assumptions!$F$20*F$41))/($C$6*$C$7)) -> 7.9952778 | G43: =IF(OR(G$41=0,$C$6*$C$7=0),0,($C43/(Assumptions!$F$20*G$41))/($C$6*$C$7)) -> 6.5415909 | H43: =IF(OR(H$41=0,$C$6*$C$7=0),0,($C43/(Assumptions!$F$20*H$41))/($C$6*$C$7)) -> 5.7566 | I43: =IF(OR(I$41=0,$C$6*$C$7=0),0,($C43/(Assumptions!$F$20*I$41))/($C$6*$C$7)) -> 5.1398215 | J43: =IF(OR(J$41=0,$C$6*$C$7=0),0,($C43/(Assumptions!$F$20*J$41))/($C$6*$C$7)) -> 4.4973438
C44: 0.8 | D44: =IF(OR(D$41=0,$C$6*$C$7=0),0,($C44/(Assumptions!$F$20*D$41))/($C$6*$C$7)) -> 15.990556 | E44: =IF(OR(E$41=0,$C$6*$C$7=0),0,($C44/(Assumptions!$F$20*E$41))/($C$6*$C$7)) -> 12.792445 | F44: =IF(OR(F$41=0,$C$6*$C$7=0),0,($C44/(Assumptions!$F$20*F$41))/($C$6*$C$7)) -> 10.66037 | G44: =IF(OR(G$41=0,$C$6*$C$7=0),0,($C44/(Assumptions!$F$20*G$41))/($C$6*$C$7)) -> 8.7221213 | H44: =IF(OR(H$41=0,$C$6*$C$7=0),0,($C44/(Assumptions!$F$20*H$41))/($C$6*$C$7)) -> 7.6754667 | I44: =IF(OR(I$41=0,$C$6*$C$7=0),0,($C44/(Assumptions!$F$20*I$41))/($C$6*$C$7)) -> 6.8530953 | J44: =IF(OR(J$41=0,$C$6*$C$7=0),0,($C44/(Assumptions!$F$20*J$41))/($C$6*$C$7)) -> 5.9964584
C45: 1 | D45: =IF(OR(D$41=0,$C$6*$C$7=0),0,($C45/(Assumptions!$F$20*D$41))/($C$6*$C$7)) -> 19.988195 | E45: =IF(OR(E$41=0,$C$6*$C$7=0),0,($C45/(Assumptions!$F$20*E$41))/($C$6*$C$7)) -> 15.990556 | F45: =IF(OR(F$41=0,$C$6*$C$7=0),0,($C45/(Assumptions!$F$20*F$41))/($C$6*$C$7)) -> 13.325463 | G45: =IF(OR(G$41=0,$C$6*$C$7=0),0,($C45/(Assumptions!$F$20*G$41))/($C$6*$C$7)) -> 10.902652 | H45: =IF(OR(H$41=0,$C$6*$C$7=0),0,($C45/(Assumptions!$F$20*H$41))/($C$6*$C$7)) -> 9.5943334 | I45: =IF(OR(I$41=0,$C$6*$C$7=0),0,($C45/(Assumptions!$F$20*I$41))/($C$6*$C$7)) -> 8.5663691 | J45: =IF(OR(J$41=0,$C$6*$C$7=0),0,($C45/(Assumptions!$F$20*J$41))/($C$6*$C$7)) -> 7.495573
C46: 1.2 | D46: =IF(OR(D$41=0,$C$6*$C$7=0),0,($C46/(Assumptions!$F$20*D$41))/($C$6*$C$7)) -> 23.985833 | E46: =IF(OR(E$41=0,$C$6*$C$7=0),0,($C46/(Assumptions!$F$20*E$41))/($C$6*$C$7)) -> 19.188667 | F46: =IF(OR(F$41=0,$C$6*$C$7=0),0,($C46/(Assumptions!$F$20*F$41))/($C$6*$C$7)) -> 15.990556 | G46: =IF(OR(G$41=0,$C$6*$C$7=0),0,($C46/(Assumptions!$F$20*G$41))/($C$6*$C$7)) -> 13.083182 | H46: =IF(OR(H$41=0,$C$6*$C$7=0),0,($C46/(Assumptions!$F$20*H$41))/($C$6*$C$7)) -> 11.5132 | I46: =IF(OR(I$41=0,$C$6*$C$7=0),0,($C46/(Assumptions!$F$20*I$41))/($C$6*$C$7)) -> 10.279643 | J46: =IF(OR(J$41=0,$C$6*$C$7=0),0,($C46/(Assumptions!$F$20*J$41))/($C$6*$C$7)) -> 8.9946876
C47: 1.5 | D47: =IF(OR(D$41=0,$C$6*$C$7=0),0,($C47/(Assumptions!$F$20*D$41))/($C$6*$C$7)) -> 29.982292 | E47: =IF(OR(E$41=0,$C$6*$C$7=0),0,($C47/(Assumptions!$F$20*E$41))/($C$6*$C$7)) -> 23.985833 | F47: =IF(OR(F$41=0,$C$6*$C$7=0),0,($C47/(Assumptions!$F$20*F$41))/($C$6*$C$7)) -> 19.988195 | G47: =IF(OR(G$41=0,$C$6*$C$7=0),0,($C47/(Assumptions!$F$20*G$41))/($C$6*$C$7)) -> 16.353977 | H47: =IF(OR(H$41=0,$C$6*$C$7=0),0,($C47/(Assumptions!$F$20*H$41))/($C$6*$C$7)) -> 14.3915 | I47: =IF(OR(I$41=0,$C$6*$C$7=0),0,($C47/(Assumptions!$F$20*I$41))/($C$6*$C$7)) -> 12.849554 | J47: =IF(OR(J$41=0,$C$6*$C$7=0),0,($C47/(Assumptions!$F$20*J$41))/($C$6*$C$7)) -> 11.243359
C48: 2 | D48: =IF(OR(D$41=0,$C$6*$C$7=0),0,($C48/(Assumptions!$F$20*D$41))/($C$6*$C$7)) -> 39.976389 | E48: =IF(OR(E$41=0,$C$6*$C$7=0),0,($C48/(Assumptions!$F$20*E$41))/($C$6*$C$7)) -> 31.981111 | F48: =IF(OR(F$41=0,$C$6*$C$7=0),0,($C48/(Assumptions!$F$20*F$41))/($C$6*$C$7)) -> 26.650926 | G48: =IF(OR(G$41=0,$C$6*$C$7=0),0,($C48/(Assumptions!$F$20*G$41))/($C$6*$C$7)) -> 21.805303 | H48: =IF(OR(H$41=0,$C$6*$C$7=0),0,($C48/(Assumptions!$F$20*H$41))/($C$6*$C$7)) -> 19.188667 | I48: =IF(OR(I$41=0,$C$6*$C$7=0),0,($C48/(Assumptions!$F$20*I$41))/($C$6*$C$7)) -> 17.132738 | J48: =IF(OR(J$41=0,$C$6*$C$7=0),0,($C48/(Assumptions!$F$20*J$41))/($C$6*$C$7)) -> 14.991146

Sheet Dashboard
B2: DASHBOARD
B3: Headline outputs on the live scenario. Change Assumptions!B5 to switch case.
B5: Active scenario | C5: =Assumptions!B6 -> Base
B7: SCALE AT MONTH 36
B8: Active customers | C8: =Cohorts!AL21 -> 1703.3872
B9: MRR | C9: ='P&L'!AL18 -> 19527.207
B10: ARR (run-rate) | C10: ='P&L'!AL19 -> 234326.48 | E10: Month 36 MRR annualised.
B11: Gross margin | C11: ='P&L'!AL31 -> 0.89851888
B12: Total revenue, 36 months | C12: =SUM('P&L'!C18:AL18) -> 233772.27
B13: Total billings, 36 months | C13: =SUM('P&L'!C12:AL12) -> 261628.02 | E13: Higher than revenue by the deferred balance still unearned at month 36.
B15: PROFITABILITY & CASH
B16: Cumulative EBITDA, 36 months | C16: ='P&L'!AL42 -> 49272.658
B17: First EBITDA-positive month | C17: =IF(MIN('P&L'!C44:AL44)>36,"none in 36m",MIN('P&L'!C44:AL44)) -> 10 | E17: Accounting breakeven.
B18: First cash-flow-positive month | C18: =IF(MIN('Cash Flow'!C27:AL27)>36,"none in 36m",MIN('Cash Flow'!C27:AL27)) -> 7 | E18: Earlier than EBITDA breakeven, because annual customers pay before you earn it.
B19: Lowest cash balance | C19: =MIN('Cash Flow'!C13:AL13) -> -717.8977
B20: Additional funding required | C20: =MAX(0,-MIN('Cash Flow'!C13:AL13)) -> 717.8977 | E20: Cash needed on top of the opening balance to avoid going negative. Zero means the opening contribution carries it.
B21: Closing cash, month 36 | C21: ='Cash Flow'!AL13 -> 82128.413
B22: Deferred revenue, month 36 | C22: ='Cash Flow'!AL19 -> 27855.755 | E22: A liability. It is cash you hold but have not earned — do not read it as profit.
B24: UNIT ECONOMICS
B25: LTV | C25: ='Unit Economics'!C11 -> 193.52727
B26: Paid CAC | C26: ='Unit Economics'!C14 -> 90.909091
B27: LTV : CAC (paid) | C27: ='Unit Economics'!C20 -> 2.1288 | E27: 3.0x is the conventional bar. Below it, growth destroys value.
B28: CAC payback (paid) | C28: ='Unit Economics'!C22 -> 8.7221213 | E28: Months.
B29: Average customer lifetime | C29: ='Unit Economics'!C10 -> 18.567652 | E29: Months. Payback above this line means the business never repays acquisition.
B30: Profitable months after payback | C30: ='Unit Economics'!C24 -> 9.8455307 | E30: The earning window per customer.
B32: VALUATION
B33: NPV of net cash flow, 36 months | C33: =NPV(Assumptions!$F$54,'Cash Flow'!C12:AL12) -> 42143.458 | E33: Discounted at the monthly equivalent of the scenario's annual rate. Excludes terminal value — a 36-month NPV alone will understate any business that is still compounding at month 36.
B34: Integrity check (must be 0) | C34: =SUM('Cash Flow'!C24:AL24) -> 0 | E34: Sum of the monthly cash-to-EBITDA reconciliation. Anything other than zero invalidates the sheet.
